Workbook

Sheet Menu
A2: FRSH Daily Menu
A5: Days | B5: Recipe Code | C5: Recipe Names | D5: Category
A6: Sunday | B6: ='Master Recipes'!A10 -> RCP-Frsh-00007 | C6: Curry nomi Pasta | D6: Plates
A7: Sunday | B7: ='Master Recipes'!A14 -> RCP-Frsh-00011 | C7: Chicken Molokheya | D7: Plates
A8: Sunday | B8: ='Master Recipes'!A15 -> RCP-Frsh-00012 | C8: Egg avocado Truffle | D8: Sandwich
A9: Sunday | B9: ='Master Recipes'!A11 -> RCP-Frsh-00008 | C9: Black Lemon Steak | D9: Plates
A10: Sunday | B10: ='Master Recipes'!A16 -> RCP-Frsh-00013 | C10: Tuna truffle | D10: Sandwich
A11: Sunday | B11: ='Master Recipes'!A17 -> RCP-Frsh-00014 | C11: Chicken pumpkin | D11: Plates
A12: Sunday | B12: ='Master Recipes'!A13 -> RCP-Frsh-00010 | C12: Philly steak mushroom / Sandwich | D12: Sandwich
A13: Sunday | B13: ='Master Recipes'!A12 -> RCP-Frsh-00009 | C13: Musakhan chicken | D13: Plates
A14: Sunday | B14: ='Master Recipes'!A46 -> RCP-Frsh-00042 | C14: Ranch Salad | D14: Salad
A15: Sunday | B15: ='Master Recipes'!A48 -> RCP-Frsh-00044 | C15: Tuna Salad | D15: Salad
A16: Sunday | B16: ='Master Recipes'!A49 -> RCP-Frsh-00045 | C16: Beetroot Salad | D16: Salad
A17: Sunday | B17: ='Master Recipes'!A47 -> RCP-Frsh-00043 | C17: Grilled ranch salad | D17: Salad
A18: Sunday | B18: ='Master Recipes'!A50 -> RCP-Frsh-00046 | C18: Red beans salad | D18: Salad
A19: Sunday | B19: ='Master Recipes'!A45 -> RCP-Frsh-00041 | C19: Grilled Halloumi salad | D19: Salad
A20: Sunday | B20: ='Master Recipes'!A39 -> RCP-Frsh-00047 | C20: Mango Oats | D20: Snack
A21: Sunday | B21: ='Master Recipes'!A43 -> RCP-Frsh-00039 | C21: Coconut Dates Balls | D21: Snack
A22: Sunday | B22: ='Master Recipes'!A44 -> RCP-Frsh-00040 | C22: Cinnamon Dates Balls | D22: Snack
A23: Sunday | B23: ='Master Recipes'!A40 -> RCP-Frsh-00036 | C23: Peanut Butter Oats | D23: Snack
A24: Sunday | B24: ='Master Recipes'!A41 -> RCP-Frsh-00037 | C24: Arabian Sesame Dates Balls | D24: Snack
A25: Sunday | B25: ='Master Recipes'!A42 -> RCP-Frsh-00038 | C25: Chocolate Date Balls | D25: Snack
A26: Monday | B26: ='Master Recipes'!A20 -> RCP-Frsh-00017 | C26: Egg Mashed Potato | D26: Plates
A27: Monday | B27: ='Master Recipes'!A21 -> RCP-Frsh-00018 | C27: Caramelized PB and honey crunch | D27: Sandwich
A28: Monday | B28: ='Master Recipes'!A19 -> RCP-Frsh-00016 | C28: Rustic ragu pasta | D28: Plates
A29: Monday | B29: ='Master Recipes'!A6 -> RCP-Frsh-00003 | C29: Misto chicken broccoli | D29: Plates
A30: Monday | B30: ='Master Recipes'!A22 -> RCP-Frsh-00019 | C30: Umami Truffle streak | D30: Sandwich
A31: Monday | B31: ='Master Recipes'!A38 -> RCP-Frsh-00035 | C31: Mix Cheese | D31: Sandwich
A32: Monday | B32: ='Master Recipes'!A23 -> RCP-Frsh-00020 | C32: Tomato halloumi grilled | D32: Sandwich
A33: Monday | B33: ='Master Recipes'!A18 -> RCP-Frsh-00015 | C33: Chicken Creamy Mint | D33: Plates
A34: Monday | B34: =B14 -> RCP-Frsh-00042 | C34: Ranch Salad | D34: Salad
A35: Monday | B35: =B15 -> RCP-Frsh-00044 | C35: Tuna Salad | D35: Salad
A36: Monday | B36: =B16 -> RCP-Frsh-00045 | C36: Beetroot Salad | D36: Salad
A37: Monday | B37: =B17 -> RCP-Frsh-00043 | C37: Grilled ranch salad | D37: Salad
A38: Monday | B38: =B18 -> RCP-Frsh-00046 | C38: Red beans salad | D38: Salad
A39: Monday | B39: =B19 -> RCP-Frsh-00041 | C39: Grilled Halloumi salad | D39: Salad
A40: Monday | B40: =B20 -> RCP-Frsh-00047 | C40: Mango Oats | D40: Snack
A41: Monday | B41: =B21 -> RCP-Frsh-00039 | C41: Coconut Dates Balls | D41: Snack
A42: Monday | B42: =B22 -> RCP-Frsh-00040 | C42: Cinnamon Dates Balls | D42: Snack
A43: Monday | B43: =B23 -> RCP-Frsh-00036 | C43: Peanut Butter Oats | D43: Snack
A44: Monday | B44: =B24 -> RCP-Frsh-00037 | C44: Arabian Sesame Dates Balls | D44: Snack
A45: Monday | B45: =B25 -> RCP-Frsh-00038 | C45: Chocolate Date Balls | D45: Snack
A46: Tuesday | B46: ='Master Recipes'!A24 -> RCP-Frsh-00021 | C46: Chicken Creamy Potato | D46: Plates
A47: Tuesday | B47: ='Master Recipes'!A25 -> RCP-Frsh-00022 | C47: Aromi Pasta Chicken | D47: Plates
A48: Tuesday | B48: ='Master Recipes'!A27 -> RCP-Frsh-00024 | C48: Mushroom Steak delight | D48: Plates
A49: Tuesday | B49: ='Master Recipes'!A9 -> RCP-Frsh-00006 | C49: Chicken Creamy Lemon | D49: Plates
A50: Tuesday | B50: ='Master Recipes'!A26 -> RCP-Frsh-00023 | C50: Philly Steak | D50: Sandwich
A51: Tuesday | B51: ='Master Recipes'!A7 -> RCP-Frsh-00004 | C51: Honey Pecan Halloumi | D51: Sandwich
A52: Tuesday | B52: ='Master Recipes'!A28 -> RCP-Frsh-00025 | C52: Egg Avocado with Glazy | D52: Sandwich
A53: Tuesday | B53: =B34 -> RCP-Frsh-00042 | C53: Ranch Salad | D53: Salad
A54: Tuesday | B54: =B35 -> RCP-Frsh-00044 | C54: Tuna Salad | D54: Salad
A55: Tuesday | B55: =B36 -> RCP-Frsh-00045 | C55: Beetroot Salad | D55: Salad
A56: Tuesday | B56: =B37 -> RCP-Frsh-00043 | C56: Grilled ranch salad | D56: Salad
A57: Tuesday | B57: =B38 -> RCP-Frsh-00046 | C57: Red beans salad | D57: Salad
A58: Tuesday | B58: =B39 -> RCP-Frsh-00041 | C58: Grilled Halloumi salad | D58: Salad
A59: Tuesday | B59: =B40 -> RCP-Frsh-00047 | C59: Mango Oats | D59: Snack
A60: Tuesday | B60: =B41 -> RCP-Frsh-00039 | C60: Coconut Dates Balls | D60: Snack
A61: Tuesday | B61: =B42 -> RCP-Frsh-00040 | C61: Cinnamon Dates Balls | D61: Snack
A62: Tuesday | B62: =B43 -> RCP-Frsh-00036 | C62: Peanut Butter Oats | D62: Snack
A63: Tuesday | B63: =B44 -> RCP-Frsh-00037 | C63: Arabian Sesame Dates Balls | D63: Snack
A64: Tuesday | B64: =B45 -> RCP-Frsh-00038 | C64: Chocolate Date Balls | D64: Snack
A65: Wednesday | B65: ='Master Recipes'!A17 -> RCP-Frsh-00014 | C65: Chicken Pumpkin | D65: Plates
A66: Wednesday | B66: ='Master Recipes'!A30 -> RCP-Frsh-00027 | C66: Avocado Egg Pesto | D66: Sandwich
A67: Wednesday | B67: ='Master Recipes'!A29 -> RCP-Frsh-00026 | C67: Steak Mushroom Entercoat | D67: Plates
A68: Wednesday | B68: ='Master Recipes'!A31 -> RCP-Frsh-00028 | C68: Chicken Creamy Dill | D68: Plates
A69: Wednesday | B69: ='Master Recipes'!A16 -> RCP-Frsh-00013 | C69: Tuna Truffle | D69: Sandwich
A70: Wednesday | B70: ='Master Recipes'!A38 -> RCP-Frsh-00035 | C70: Mix Cheese | D70: Sandwich
A71: Wednesday | B71: ='Master Recipes'!A32 -> RCP-Frsh-00029 | C71: Pasta Black Lemon | D71: Plates
A72: Wednesday | B72: ='Master Recipes'!A14 -> RCP-Frsh-00011 | C72: Chicken Molokheya | D72: Plates
A73: Wednesday | B73: =B53 -> RCP-Frsh-00042 | C73: Ranch Salad | D73: Salad
A74: Wednesday | B74: =B54 -> RCP-Frsh-00044 | C74: Tuna Salad | D74: Salad
A75: Wednesday | B75: =B55 -> RCP-Frsh-00045 | C75: Beetroot Salad | D75: Salad
A76: Wednesday | B76: =B56 -> RCP-Frsh-00043 | C76: Grilled ranch salad | D76: Salad
A77: Wednesday | B77: =B57 -> RCP-Frsh-00046 | C77: Red beans salad | D77: Salad
A78: Wednesday | B78: =B58 -> RCP-Frsh-00041 | C78: Grilled Halloumi salad | D78: Salad
A79: Wednesday | B79: =B59 -> RCP-Frsh-00047 | C79: Mango Oats | D79: Snack
A80: Wednesday | B80: =B60 -> RCP-Frsh-00039 | C80: Coconut Dates Balls | D80: Snack
A81: Wednesday | B81: =B61 -> RCP-Frsh-00040 | C81: Cinnamon Dates Balls | D81: Snack
A82: Wednesday | B82: =B62 -> RCP-Frsh-00036 | C82: Peanut Butter Oats | D82: Snack
A83: Wednesday | B83: =B63 -> RCP-Frsh-00037 | C83: Arabian Sesame Dates Balls | D83: Snack
A84: Wednesday | B84: =B64 -> RCP-Frsh-00038 | C84: Chocolate Date Balls | D84: Snack
A85: Thursday | B85: ='Master Recipes'!A33 -> RCP-Frsh-00030 | C85: Juicy beef pasta | D85: Plates
A86: Thursday | B86: ='Master Recipes'!A35 -> RCP-Frsh-00032 | C86: Chicken creamy sumac | D86: Plates
A87: Thursday | B87: ='Master Recipes'!A36 -> RCP-Frsh-00033 | C87: Philly steak barbecue | D87: Sandwich
A88: Thursday | B88: ='Master Recipes'!A34 -> RCP-Frsh-00031 | C88: Curry nomi | D88: Plates
A89: Thursday | B89: ='Master Recipes'!A20 -> RCP-Frsh-00017 | C89: Egg Mashed potato | D89: Plates
A90: Thursday | B90: ='Master Recipes'!A21 -> RCP-Frsh-00018 | C90: Caramelized PB and Honey Crunch | D90: Sandwich
A91: Thursday | B91: ='Master Recipes'!A23 -> RCP-Frsh-00020 | C91: Tomato Halloumi Grilled | D91: Sandwich
A92: Thursday | B92: =B73 -> RCP-Frsh-00042 | C92: Ranch Salad | D92: Salad
A93: Thursday | B93: =B74 -> RCP-Frsh-00044 | C93: Tuna Salad | D93: Salad
A94: Thursday | B94: =B75 -> RCP-Frsh-00045 | C94: Beetroot Salad | D94: Salad
A95: Thursday | B95: =B76 -> RCP-Frsh-00043 | C95: Grilled ranch salad | D95: Salad
A96: Thursday | B96: =B77 -> RCP-Frsh-00046 | C96: Red beans salad | D96: Salad
A97: Thursday | B97: =B78 -> RCP-Frsh-00041 | C97: Grilled Halloumi salad | D97: Salad
A98: Thursday | B98: =B79 -> RCP-Frsh-00047 | C98: Mango Oats | D98: Snack
A99: Thursday | B99: =B80 -> RCP-Frsh-00039 | C99: Coconut Dates Balls | D99: Snack
A100: Thursday | B100: =B81 -> RCP-Frsh-00040 | C100: Cinnamon Dates Balls | D100: Snack
A101: Thursday | B101: =B82 -> RCP-Frsh-00036 | C101: Peanut Butter Oats | D101: Snack
A102: Thursday | B102: =B83 -> RCP-Frsh-00037 | C102: Arabian Sesame Dates Balls | D102: Snack
A103: Thursday | B103: =B84 -> RCP-Frsh-00038 | C103: Chocolate Date Balls | D103: Snack
...

Sheet Master Recipes
A1: 📘 Master Recipes – Academia School
A3: Main Recipe ID | B3: Recipe Name | C3: Brand Code | D3: Customer Name | E3: Category | F3: Standard No. of Portions | G3: Weight per Portion (g) | H3: Size of Portion | I3: Has Sub Recipe? | J3: Sub Recipe ID | K3: Sub Recipe Name | L3: Sub Recipe No. of Portions | M3: Total Ingredient Count | N3: Total Batch Wt (g) * | O3: Recipe Standard Yield % | P3: Targeted Wastage % | Q3: Food Cost Per Portion | R3: Packaging Cost | S3: Labor Cost | T3: Delivery Cost | U3: Overheads | V3: Other Costs | W3: Total Cost | X3: Margin %age | Y3: Profit | Z3: Sale Price | AA3: Remark
A4: {=_xlfn.UNIQUE('Recipe Ingredients'!A5:A838)} -> RCP-Frsh-00001 | B4: =VLOOKUP(A4,'Recipe Ingredients'!$A$5:$D$838,4,0) -> Avocado egg Ranch
A5: RCP-Frsh-00002 | B5: =VLOOKUP(A5,'Recipe Ingredients'!$A$5:$D$838,4,0) -> Spinach steak
A6: RCP-Frsh-00003 | B6: =VLOOKUP(A6,'Recipe Ingredients'!$A$5:$D$838,4,0) -> Misto chicken broccoli
A7: RCP-Frsh-00004 | B7: =VLOOKUP(A7,'Recipe Ingredients'!$A$5:$D$838,4,0) -> Honey Pecan Halloumi
A8: RCP-Frsh-00005 | B8: =VLOOKUP(A8,'Recipe Ingredients'!$A$5:$D$838,4,0) -> Pasta Creamy Potato
A9: RCP-Frsh-00006 | B9: =VLOOKUP(A9,'Recipe Ingredients'!$A$5:$D$838,4,0) -> Chicken creamy lemon
A10: RCP-Frsh-00007 | B10: =VLOOKUP(A10,'Recipe Ingredients'!$A$5:$D$838,4,0) -> Curry nomi Pasta
A11: RCP-Frsh-00008 | B11: =VLOOKUP(A11,'Recipe Ingredients'!$A$5:$D$838,4,0) -> Black Lemon Steak
A12: RCP-Frsh-00009 | B12: =VLOOKUP(A12,'Recipe Ingredients'!$A$5:$D$838,4,0) -> Musakhan chicken
A13: RCP-Frsh-00010 | B13: =VLOOKUP(A13,'Recipe Ingredients'!$A$5:$D$838,4,0) -> Philly steak mushroom
A14: RCP-Frsh-00011 | B14: =VLOOKUP(A14,'Recipe Ingredients'!$A$5:$D$838,4,0) -> Chicken Molokheya
A15: RCP-Frsh-00012 | B15: =VLOOKUP(A15,'Recipe Ingredients'!$A$5:$D$838,4,0) -> Egg avocado Truffle
A16: RCP-Frsh-00013 | B16: =VLOOKUP(A16,'Recipe Ingredients'!$A$5:$D$838,4,0) -> Tuna truffle
... A50: RCP-Frsh-00046 | B50: =VLOOKUP(A50,'Recipe Ingredients'!$A$5:$D$838,4,0) -> Red Beans Salad

Sheet Recipe Ingredients
A1: 📘 Master Recipe Ingredients – FRSH
A3: ▶ CONSOLIDATED INGREDIENT MASTER — FRSH Main + Sub Recipes
A4: Recipe code | B4: Category | C4: Customer Name | D4: Recipe Name | E4: Day | F4: Section | G4: Sub Recipe Description | H4: Item Code | I4: Item / Ingredient | J4: UOM | K4: Standard UOM | L4: NET Qty req per Batch (g/pcs) | M4: GROSS Qty req per Batch (g/pcs) | N4: Yield % | O4: No. of portions per batch | P4: Qty req per portion | Q4: Purchase Price Standard UOM | R4: Food Cost per portion | S4: Veriable cost 10% | T4: Total Food Cost | U4: Labour Cost | V4: Delivery Cost | W4: Packing Cost | X4: Total cost | Y4: Buchery Cutting /Portion size
A5: RCP-Frsh-00001 | B5: Sandwiches | C5: Frsh | D5: Avocado egg Ranch | E5: Saturday | F5: TrayLine Section | H5: =IFERROR(VLOOKUP(I5,'Raw material list'!$A$3:$C$695,3,0),"") -> BKR1-1327 | I5: Bread Sliced Brown Med-400001 | J5: Slice | K5: =IFERROR(VLOOKUP(I5,'Raw material list'!$A$3:$E$695,5,0),"") -> Slice | L5: 10 | M5: =L5/N5*100 -> 10 | N5: 100 | O5: 10 | P5: =IFERROR(L5/O5,0) -> 1 | Q5: =IFERROR(VLOOKUP(I5,'Raw material list'!$A$3:$F$695,6,0),"") -> 0.22222222 | R5: =IFERROR(Q5*P5,0) -> 0.22222222 | S5: =R5*10% -> 0.022222222 | T5: =R5+S5 -> 0.24444444 | U5: =T5*10% -> 0.024444444 | V5: =T5*1% -> 0.0024444444 | W5: =T5*1% -> 0.0024444444 | X5: =T5+U5+V5+W5 -> 0.27377778
A6: RCP-Frsh-00001 | B6: Sandwiches | C6: Frsh | D6: Avocado egg Ranch | E6: Saturday | F6: Hot Section | H6: =IFERROR(VLOOKUP(I6,'Raw material list'!$A$3:$C$695,3,0),"") -> PLT1-37 | I6: Eggs | J6: Each | K6: =IFERROR(VLOOKUP(I6,'Raw material list'!$A$3:$E$695,5,0),"") -> Each | L6: 12 | M6: =L6/N6*100 -> 12 | N6: 100 | O6: 10 | P6: =IFERROR(L6/O6,0) -> 1.2 | Q6: =IFERROR(VLOOKUP(I6,'Raw material list'!$A$3:$F$695,6,0),"") -> 0.483 | R6: =IFERROR(Q6*P6,0) -> 0.5796 | S6: =R6*10% -> 0.05796 | T6: =R6+S6 -> 0.63756 | U6: =T6*10% -> 0.063756 | V6: =T6*1% -> 0.0063756 | W6: =T6*1% -> 0.0063756 | X6: =T6+U6+V6+W6 -> 0.7140672
A7: RCP-Frsh-00001 | B7: Sandwiches | C7: Frsh | D7: Avocado egg Ranch | E7: Saturday | F7: Hot Section | H7: =IFERROR(VLOOKUP(I7,'Raw material list'!$A$3:$C$695,3,0),"") -> PRD1-4787 | I7: Fresh Avocado | J7: Gram | K7: =IFERROR(VLOOKUP(I7,'Raw material list'!$A$3:$E$695,5,0),"") -> Gram | L7: 61.12 | M7: =L7/N7*100 -> 150.29508 | N7: 40.666667 | O7: 10 | P7: =IFERROR(L7/O7,0) -> 6.112 | Q7: =IFERROR(VLOOKUP(I7,'Raw material list'!$A$3:$F$695,6,0),"") -> 0.078624079 | R7: =IFERROR(Q7*P7,0) -> 0.48055037 | S7: =R7*10% -> 0.048055037 | T7: =R7+S7 -> 0.52860541 | U7: =T7*10% -> 0.052860541 | V7: =T7*1% -> 0.0052860541 | W7: =T7*1% -> 0.0052860541 | X7: =T7+U7+V7+W7 -> 0.59203805
A8: RCP-Frsh-00001 | B8: Sandwiches | C8: Frsh | D8: Avocado egg Ranch | E8: Saturday | F8: Hot Section | H8: =IFERROR(VLOOKUP(I8,'Raw material list'!$A$3:$C$695,3,0),"") -> DRS1-114 | I8: Sea Salt(737 Gram) | J8: Gram | K8: =IFERROR(VLOOKUP(I8,'Raw material list'!$A$3:$E$695,5,0),"") -> Gram | L8: 3.5 | M8: =L8/N8*100 -> 3.5 | N8: 100 | O8: 10 | P8: =IFERROR(L8/O8,0) -> 0.35 | Q8: =IFERROR(VLOOKUP(I8,'Raw material list'!$A$3:$F$695,6,0),"") -> 0.0047489824 | R8: =IFERROR(Q8*P8,0) -> 0.0016621438 | S8: =R8*10% -> 0.00016621438 | T8: =R8+S8 -> 0.0018283582 | U8: =T8*10% -> 0.00018283582 | V8: =T8*1% -> 1.8283582e-05 | W8: =T8*1% -> 1.8283582e-05 | X8: =T8+U8+V8+W8 -> 0.0020477612
A9: RCP-Frsh-00001 | B9: Sandwiches | C9: Frsh | D9: Avocado egg Ranch | E9: Saturday | F9: Hot Section | H9: =IFERROR(VLOOKUP(I9,'Raw material list'!$A$3:$C$695,3,0),"") -> DRS6-537 | I9: Spices Pepper Black Powder(1 Kg) | J9: Gram | K9: =IFERROR(VLOOKUP(I9,'Raw material list'!$A$3:$E$695,5,0),"") -> Gram | L9: 0.855 | M9: =L9/N9*100 -> 0.855 | N9: 100 | O9: 10 | P9: =IFERROR(L9/O9,0) -> 0.0855 | Q9: =IFERROR(VLOOKUP(I9,'Raw material list'!$A$3:$F$695,6,0),"") -> 0.035 | R9: =IFERROR(Q9*P9,0) -> 0.0029925 | S9: =R9*10% -> 0.00029925 | T9: =R9+S9 -> 0.00329175 | U9: =T9*10% -> 0.000329175 | V9: =T9*1% -> 3.29175e-05 | W9: =T9*1% -> 3.29175e-05 | X9: =T9+U9+V9+W9 -> 0.00368676
A10: RCP-Frsh-00001 | B10: Sandwiches | C10: Frsh | D10: Avocado egg Ranch | E10: Saturday | F10: Hot Section | H10: =IFERROR(VLOOKUP(I10,'Raw material list'!$A$3:$C$695,3,0),"") -> DRS6-309 | I10: Spice Pepper White Powder | J10: Gram | K10: =IFERROR(VLOOKUP(I10,'Raw material list'!$A$3:$E$695,5,0),"") -> Gram | L10: 0.855 | M10: =L10/N10*100 -> 0.855 | N10: 100 | O10: 10 | P10: =IFERROR(L10/O10,0) -> 0.0855 | Q10: =IFERROR(VLOOKUP(I10,'Raw material list'!$A$3:$F$695,6,0),"") -> 0.028 | R10: =IFERROR(Q10*P10,0) -> 0.002394 | S10: =R10*10% -> 0.0002394 | T10: =R10+S10 -> 0.0026334 | U10: =T10*10% -> 0.00026334 | V10: =T10*1% -> 2.6334e-05 | W10: =T10*1% -> 2.6334e-05 | X10: =T10+U10+V10+W10 -> 0.002949408
A11: RCP-Frsh-00001 | B11: Sandwiches | C11: Frsh | D11: Avocado egg Ranch | E11: Saturday | F11: Hot Section | H11: =IFERROR(VLOOKUP(I11,'Raw material list'!$A$3:$C$695,3,0),"") -> DRS6-1570 | I11: Dried Oregano | J11: Gram | K11: =IFERROR(VLOOKUP(I11,'Raw material list'!$A$3:$E$695,5,0),"") -> Gram | L11: 0.611 | M11: =L11/N11*100 -> 0.611 | N11: 100 | O11: 10 | P11: =IFERROR(L11/O11,0) -> 0.0611 | Q11: =IFERROR(VLOOKUP(I11,'Raw material list'!$A$3:$F$695,6,0),"") -> 0.028 | R11: =IFERROR(Q11*P11,0) -> 0.0017108 | S11: =R11*10% -> 0.00017108 | T11: =R11+S11 -> 0.00188188 | U11: =T11*10% -> 0.000188188 | V11: =T11*1% -> 1.88188e-05 | W11: =T11*1% -> 1.88188e-05 | X11: =T11+U11+V11+W11 -> 0.0021077056
A12: RCP-Frsh-00001 | B12: Sandwiches | C12: Frsh | D12: Avocado egg Ranch | E12: Saturday | F12: Hot Section | G12: Ranch Sauce | H12: =IFERROR(VLOOKUP(I12,'Raw material list'!$A$3:$C$695,3,0),"") -> DRS1-1652 | I12: Light Mayonnaise | J12: Gram | K12: =IFERROR(VLOOKUP(I12,'Raw material list'!$A$3:$E$695,5,0),"") -> Gram | L12: 67.64 | M12: =L12/N12*100 -> 67.64 | N12: 100 | O12: 10 | P12: =IFERROR(L12/O12,0) -> 6.764 | Q12: =IFERROR(VLOOKUP(I12,'Raw material list'!$A$3:$F$695,6,0),"") -> 0.0128 | R12: =IFERROR(Q12*P12,0) -> 0.0865792 | S12: =R12*10% -> 0.00865792 | T12: =R12+S12 -> 0.09523712 | U12: =T12*10% -> 0.009523712 | V12: =T12*1% -> 0.0009523712 | W12: =T12*1% -> 0.0009523712 | X12: =T12+U12+V12+W12 -> 0.10666557
A13: RCP-Frsh-00001 | B13: Sandwiches | C13: Frsh | D13: Avocado egg Ranch | E13: Saturday | F13: Hot Section | G13: Ranch Sauce | H13: =IFERROR(VLOOKUP(I13,'Raw material list'!$A$3:$C$695,3,0),"") -> DRY1-1717 | I13: Cheese Cream Philadelphia (1360 GR) | J13: Gram | K13: =IFERROR(VLOOKUP(I13,'Raw material list'!$A$3:$E$695,5,0),"") -> Gram | L13: 33.82 | M13: =L13/N13*100 -> 33.82 | N13: 100 | O13: 10 | P13: =IFERROR(L13/O13,0) -> 3.382 | Q13: =IFERROR(VLOOKUP(I13,'Raw material list'!$A$3:$F$695,6,0),"") -> 0.037 | R13: =IFERROR(Q13*P13,0) -> 0.125134 | S13: =R13*10% -> 0.0125134 | T13: =R13+S13 -> 0.1376474 | U13: =T13*10% -> 0.01376474 | V13: =T13*1% -> 0.001376474 | W13: =T13*1% -> 0.001376474 | X13: =T13+U13+V13+W13 -> 0.15416509
A14: RCP-Frsh-00001 | B14: Sandwiches | C14: Frsh | D14: Avocado egg Ranch | E14: Saturday | F14: Hot Section | G14: Ranch Sauce | H14: =IFERROR(VLOOKUP(I14,'Raw material list'!$A$3:$C$695,3,0),"") -> PRD1-209 | I14: Fresh Lemon | J14: Gram | K14: =IFERROR(VLOOKUP(I14,'Raw material list'!$A$3:$E$695,5,0),"") -> Gram | L14: 0.67 | M14: =L14/N14*100 -> 1.7631579 | N14: 38 | O14: 10 | P14: =IFERROR(L14/O14,0) -> 0.067 | Q14: =IFERROR(VLOOKUP(I14,'Raw material list'!$A$3:$F$695,6,0),"") -> 0.010088272 | R14: =IFERROR(Q14*P14,0) -> 0.00067591425 | S14: =R14*10% -> 6.7591425e-05 | T14: =R14+S14 -> 0.00074350567 | U14: =T14*10% -> 7.4350567e-05 | V14: =T14*1% -> 7.4350567e-06 | W14: =T14*1% -> 7.4350567e-06 | X14: =T14+U14+V14+W14 -> 0.00083272636
A15: RCP-Frsh-00001 | B15: Sandwiches | C15: Frsh | D15: Avocado egg Ranch | E15: Saturday | F15: Hot Section | G15: Ranch Sauce | H15: =IFERROR(VLOOKUP(I15,'Raw material list'!$A$3:$C$695,3,0),"") -> DRS6-537 | I15: Spices Pepper Black Powder(1 Kg) | J15: Gram | K15: =IFERROR(VLOOKUP(I15,'Raw material list'!$A$3:$E$695,5,0),"") -> Gram | L15: 0.27 | M15: =L15/N15*100 -> 0.27 | N15: 100 | O15: 10 | P15: =IFERROR(L15/O15,0) -> 0.027 | Q15: =IFERROR(VLOOKUP(I15,'Raw material list'!$A$3:$F$695,6,0),"") -> 0.035 | R15: =IFERROR(Q15*P15,0) -> 0.000945 | S15: =R15*10% -> 9.45e-05 | T15: =R15+S15 -> 0.0010395 | U15: =T15*10% -> 0.00010395 | V15: =T15*1% -> 1.0395e-05 | W15: =T15*1% -> 1.0395e-05 | X15: =T15+U15+V15+W15 -> 0.00116424
A16: RCP-Frsh-00001 | B16: Sandwiches | C16: Frsh | D16: Avocado egg Ranch | E16: Saturday | F16: Hot Section | G16: Ranch Sauce | H16: =IFERROR(VLOOKUP(I16,'Raw material list'!$A$3:$C$695,3,0),"") -> DRS1-114 | I16: Sea Salt(737 Gram) | J16: Gram | K16: =IFERROR(VLOOKUP(I16,'Raw material list'!$A$3:$E$695,5,0),"") -> Gram | L16: 0.27 | M16: =L16/N16*100 -> 0.27 | N16: 100 | O16: 10 | P16: =IFERROR(L16/O16,0) -> 0.027 | Q16: =IFERROR(VLOOKUP(I16,'Raw material list'!$A$3:$F$695,6,0),"") -> 0.0047489824 | R16: =IFERROR(Q16*P16,0) -> 0.00012822252 | S16: =R16*10% -> 1.2822252e-05 | T16: =R16+S16 -> 0.00014104478 | U16: =T16*10% -> 1.4104478e-05 | V16: =T16*1% -> 1.4104478e-06 | W16: =T16*1% -> 1.4104478e-06 | X16: =T16+U16+V16+W16 -> 0.00015797015
A17: RCP-Frsh-00001 | B17: Sandwiches | C17: Frsh | D17: Avocado egg Ranch | E17: Saturday | F17: Hot Section | G17: Ranch Sauce | H17: =IFERROR(VLOOKUP(I17,'Raw material list'!$A$3:$C$695,3,0),"") -> WAT-001 | I17: Tap Water-cooking | J17: Ml | K17: =IFERROR(VLOOKUP(I17,'Raw material list'!$A$3:$E$695,5,0),"") -> Ml | L17: 6.76 | M17: =L17/N17*100 -> 6.76 | N17: 100 | O17: 10 | P17: =IFERROR(L17/O17,0) -> 0.676 | Q17: =IFERROR(VLOOKUP(I17,'Raw material list'!$A$3:$F$695,6,0),"") -> 8e-05 | R17: =IFERROR(Q17*P17,0) -> 5.408e-05 | S17: =R17*10% -> 5.408e-06 | T17: =R17+S17 -> 5.9488e-05 | U17: =T17*10% -> 5.9488e-06 | V17: =T17*1% -> 5.9488e-07 | W17: =T17*1% -> 5.9488e-07 | X17: =T17+U17+V17+W17 -> 6.662656e-05
A18: RCP-Frsh-00001 | B18: Sandwiches | C18: Frsh | D18: Avocado egg Ranch | E18: Saturday | F18: Hot Section | G18: Ranch Sauce | H18: =IFERROR(VLOOKUP(I18,'Raw material list'!$A$3:$C$695,3,0),"") -> DRS1-5273 | I18: Sauce Worcester L&P 3.78 Ltr | J18: Ml | K18: =IFERROR(VLOOKUP(I18,'Raw material list'!$A$3:$E$695,5,0),"") -> Ml | L18: 1.35 | M18: =L18/N18*100 -> 1.35 | N18: 100 | O18: 10 | P18: =IFERROR(L18/O18,0) -> 0.135 | Q18: =IFERROR(VLOOKUP(I18,'Raw material list'!$A$3:$F$695,6,0),"") -> 0.018518519 | R18: =IFERROR(Q18*P18,0) -> 0.0025 | S18: =R18*10% -> 0.00025 | T18: =R18+S18 -> 0.00275 | U18: =T18*10% -> 0.000275 | V18: =T18*1% -> 2.75e-05 | W18: =T18*1% -> 2.75e-05 | X18: =T18+U18+V18+W18 -> 0.00308
A19: RCP-Frsh-00001 | B19: Sandwiches | C19: Frsh | D19: Avocado egg Ranch | E19: Saturday | F19: Hot Section | G19: Ranch Sauce | H19: =IFERROR(VLOOKUP(I19,'Raw material list'!$A$3:$C$695,3,0),"") -> DRS1-5269 | I19: Maple Syrup Amber 375 ml | J19: Ml | K19: =IFERROR(VLOOKUP(I19,'Raw material list'!$A$3:$E$695,5,0),"") -> Ml | L19: 1.35 | M19: =L19/N19*100 -> 1.35 | N19: 100 | O19: 10 | P19: =IFERROR(L19/O19,0) -> 0.135 | Q19: =IFERROR(VLOOKUP(I19,'Raw material list'!$A$3:$F$695,6,0),"") -> 0.10666667 | R19: =IFERROR(Q19*P19,0) -> 0.0144 | S19: =R19*10% -> 0.00144 | T19: =R19+S19 -> 0.01584 | U19: =T19*10% -> 0.001584 | V19: =T19*1% -> 0.0001584 | W19: =T19*1% -> 0.0001584 | X19: =T19+U19+V19+W19 -> 0.0177408
A20: RCP-Frsh-00001 | B20: Sandwiches | C20: Frsh | D20: Avocado egg Ranch | E20: Saturday | F20: Hot Section | G20: Ranch Sauce | H20: =IFERROR(VLOOKUP(I20,'Raw material list'!$A$3:$C$695,3,0),"") -> DRY2-1858 | I20: Cooking Cream 1 Ltr | J20: Ml | K20: =IFERROR(VLOOKUP(I20,'Raw material list'!$A$3:$E$695,5,0),"") -> Ml | L20: 6.76 | M20: =L20/N20*100 -> 6.76 | N20: 100 | O20: 10 | P20: =IFERROR(L20/O20,0) -> 0.676 | Q20: =IFERROR(VLOOKUP(I20,'Raw material list'!$A$3:$F$695,6,0),"") -> 0.00988 | R20: =IFERROR(Q20*P20,0) -> 0.00667888 | S20: =R20*10% -> 0.000667888 | T20: =R20+S20 -> 0.007346768 | U20: =T20*10% -> 0.0007346768 | V20: =T20*1% -> 7.346768e-05 | W20: =T20*1% -> 7.346768e-05 | X20: =T20+U20+V20+W20 -> 0.0082283802
A21: RCP-Frsh-00001 | B21: Sandwiches | C21: Frsh | D21: Avocado egg Ranch | E21: Saturday | F21: Hot Section | G21: Ranch Sauce | H21: =IFERROR(VLOOKUP(I21,'Raw material list'!$A$3:$C$695,3,0),"") -> PRD1-221 | I21: Fresh Mint | J21: Gram | K21: =IFERROR(VLOOKUP(I21,'Raw material list'!$A$3:$E$695,5,0),"") -> Gram | L21: 1.082 | M21: =L21/N21*100 -> 1.8612385 | N21: 58.133333 | O21: 10 | P21: =IFERROR(L21/O21,0) -> 0.1082 | Q21: =IFERROR(VLOOKUP(I21,'Raw material list'!$A$3:$F$695,6,0),"") -> 0.0068846816 | R21: =IFERROR(Q21*P21,0) -> 0.00074492255 | S21: =R21*10% -> 7.4492255e-05 | T21: =R21+S21 -> 0.0008194148 | U21: =T21*10% -> 8.194148e-05 | V21: =T21*1% -> 8.194148e-06 | W21: =T21*1% -> 8.194148e-06 | X21: =T21+U21+V21+W21 -> 0.00091774458
A22: RCP-Frsh-00001 | B22: Sandwiches | C22: Frsh | D22: Avocado egg Ranch | E22: Saturday | F22: TrayLine Section | G22: Garnish | H22: =IFERROR(VLOOKUP(I22,'Raw material list'!$A$3:$C$695,3,0),"") -> PRD1-235 | I22: Fresh Rocket | J22: Gram | K22: =IFERROR(VLOOKUP(I22,'Raw material list'!$A$3:$E$695,5,0),"") -> Gram | L22: 30 | M22: =L22/N22*100 -> 92.783505 | N22: 32.333333 | O22: 10 | P22: =IFERROR(L22/O22,0) -> 3 | Q22: =IFERROR(VLOOKUP(I22,'Raw material list'!$A$3:$F$695,6,0),"") -> 0.012383901 | R22: =IFERROR(Q22*P22,0) -> 0.037151703 | S22: =R22*10% -> 0.0037151703 | T22: =R22+S22 -> 0.040866873 | U22: =T22*10% -> 0.0040866873 | V22: =T22*1% -> 0.00040866873 | W22: =T22*1% -> 0.00040866873 | X22: =T22+U22+V22+W22 -> 0.045770898
A23: RCP-Frsh-00002 | B23: Plates | C23: Frsh | D23: Spinach steak | E23: Saturday | F23: Butchery Section | G23: Beef marination | H23: =IFERROR(VLOOKUP(I23,'Raw material list'!$A$3:$C$695,3,0),"") -> MET2-1051 | I23: Frz Beef Tendrloin Brazil | J23: Gram | K23: =IFERROR(VLOOKUP(I23,'Raw material list'!$A$3:$E$695,5,0),"") -> Gram | L23: 1500 | M23: =L23/N23*100 -> 2918.2879 | N23: 51.4 | O23: 10 | P23: =IFERROR(L23/O23,0) -> 150 | Q23: =IFERROR(VLOOKUP(I23,'Raw material list'!$A$3:$F$695,6,0),"") -> 0.084705882 | R23: =IFERROR(Q23*P23,0) -> 12.705882 | S23: =R23*10% -> 1.2705882 | T23: =R23+S23 -> 13.976471 | U23: =T23*10% -> 1.3976471 | V23: =T23*1% -> 0.13976471 | W23: =T23*1% -> 0.13976471 | X23: =T23+U23+V23+W23 -> 15.653647 | Y23: Beef Tenderloin - Pc - 160 g
A24: RCP-Frsh-00002 | B24: Plates | C24: Frsh | D24: Spinach steak | E24: Saturday | F24: Butchery Section | G24: Beef marination | H24: =IFERROR(VLOOKUP(I24,'Raw material list'!$A$3:$C$695,3,0),"") -> DRS1-1142 | I24: Soya Sauce Kikkoman(Liter) | J24: Gram | K24: =IFERROR(VLOOKUP(I24,'Raw material list'!$A$3:$E$695,5,0),"") -> Ml | L24: 100 | M24: =L24/N24*100 -> 100 | N24: 100 | O24: 10 | P24: =IFERROR(L24/O24,0) -> 10 | Q24: =IFERROR(VLOOKUP(I24,'Raw material list'!$A$3:$F$695,6,0),"") -> 0.02358 | R24: =IFERROR(Q24*P24,0) -> 0.2358 | S24: =R24*10% -> 0.02358 | T24: =R24+S24 -> 0.25938 | U24: =T24*10% -> 0.025938 | V24: =T24*1% -> 0.0025938 | W24: =T24*1% -> 0.0025938 | X24: =T24+U24+V24+W24 -> 0.2905056
A25: RCP-Frsh-00002 | B25: Plates | C25: Frsh | D25: Spinach steak | E25: Saturday | F25: Butchery Section | G25: Beef marination | H25: =IFERROR(VLOOKUP(I25,'Raw material list'!$A$3:$C$695,3,0),"") -> PRD1-4327 | I25: Fresh Garlic Peeled | J25: Gram | K25: =IFERROR(VLOOKUP(I25,'Raw material list'!$A$3:$E$695,5,0),"") -> Gram | L25: 10 | M25: =L25/N25*100 -> 12.5 | N25: 80 | O25: 10 | P25: =IFERROR(L25/O25,0) -> 1 | Q25: =IFERROR(VLOOKUP(I25,'Raw material list'!$A$3:$F$695,6,0),"") -> 0.013 | R25: =IFERROR(Q25*P25,0) -> 0.013 | S25: =R25*10% -> 0.0013 | T25: =R25+S25 -> 0.0143 | U25: =T25*10% -> 0.00143 | V25: =T25*1% -> 0.000143 | W25: =T25*1% -> 0.000143 | X25: =T25+U25+V25+W25 -> 0.016016
A26: RCP-Frsh-00002 | B26: Plates | C26: Frsh | D26: Spinach steak | E26: Saturday | F26: Butchery Section | G26: Beef marination | H26: =IFERROR(VLOOKUP(I26,'Raw material list'!$A$3:$C$695,3,0),"") -> PRD1-209 | I26: Fresh Lemon | J26: Gram | K26: =IFERROR(VLOOKUP(I26,'Raw material list'!$A$3:$E$695,5,0),"") -> Gram | L26: 15 | M26: =L26/N26*100 -> 39.473684 | N26: 38 | O26: 10 | P26: =IFERROR(L26/O26,0) -> 1.5 | Q26: =IFERROR(VLOOKUP(I26,'Raw material list'!$A$3:$F$695,6,0),"") -> 0.010088272 | R26: =IFERROR(Q26*P26,0) -> 0.015132409 | S26: =R26*10% -> 0.0015132409 | T26: =R26+S26 -> 0.016645649 | U26: =T26*10% -> 0.0016645649 | V26: =T26*1% -> 0.00016645649 | W26: =T26*1% -> 0.00016645649 | X26: =T26+U26+V26+W26 -> 0.018643127
A27: RCP-Frsh-00002 | B27: Plates | C27: Frsh | D27: Spinach steak | E27: Saturday | F27: Butchery Section | G27: Beef marination | H27: =IFERROR(VLOOKUP(I27,'Raw material list'!$A$3:$C$695,3,0),"") -> DRS6-537 | I27: Spices Pepper Black Powder(1 Kg) | J27: Gram | K27: =IFERROR(VLOOKUP(I27,'Raw material list'!$A$3:$E$695,5,0),"") -> Gram | L27: 1 | M27: =L27/N27*100 -> 1 | N27: 100 | O27: 10 | P27: =IFERROR(L27/O27,0) -> 0.1 | Q27: =IFERROR(VLOOKUP(I27,'Raw material list'!$A$3:$F$695,6,0),"") -> 0.035 | R27: =IFERROR(Q27*P27,0) -> 0.0035 | S27: =R27*10% -> 0.00035 | T27: =R27+S27 -> 0.00385 | U27: =T27*10% -> 0.000385 | V27: =T27*1% -> 3.85e-05 | W27: =T27*1% -> 3.85e-05 | X27: =T27+U27+V27+W27 -> 0.004312
A28: RCP-Frsh-00002 | B28: Plates | C28: Frsh | D28: Spinach steak | E28: Saturday | F28: Butchery Section | G28: Beef marination | H28: =IFERROR(VLOOKUP(I28,'Raw material list'!$A$3:$C$695,3,0),"") -> WAT-001 | I28: Tap Water-cooking | J28: Gram | K28: =IFERROR(VLOOKUP(I28,'Raw material list'!$A$3:$E$695,5,0),"") -> Ml | L28: 100 | M28: =L28/N28*100 -> 100 | N28: 100 | O28: 10 | P28: =IFERROR(L28/O28,0) -> 10 | Q28: =IFERROR(VLOOKUP(I28,'Raw material list'!$A$3:$F$695,6,0),"") -> 8e-05 | R28: =IFERROR(Q28*P28,0) -> 0.0008 | S28: =R28*10% -> 8e-05 | T28: =R28+S28 -> 0.00088 | U28: =T28*10% -> 8.8e-05 | V28: =T28*1% -> 8.8e-06 | W28: =T28*1% -> 8.8e-06 | X28: =T28+U28+V28+W28 -> 0.0009856
A29: RCP-Frsh-00002 | B29: Plates | C29: Frsh | D29: Spinach steak | E29: Saturday | F29: Butchery Section | G29: Beef marination | H29: =IFERROR(VLOOKUP(I29,'Raw material list'!$A$3:$C$695,3,0),"") -> PRD1-573 | I29: Fresh Spring Onion Green | J29: Gram | K29: =IFERROR(VLOOKUP(I29,'Raw material list'!$A$3:$E$695,5,0),"") -> Gram | L29: 10 | M29: =L29/N29*100 -> 13.69863 | N29: 73 | O29: 10 | P29: =IFERROR(L29/O29,0) -> 1 | Q29: =IFERROR(VLOOKUP(I29,'Raw material list'!$A$3:$F$695,6,0),"") -> 0.0054794521 | R29: =IFERROR(Q29*P29,0) -> 0.0054794521 | S29: =R29*10% -> 0.00054794521 | T29: =R29+S29 -> 0.0060273973 | U29: =T29*10% -> 0.00060273973 | V29: =T29*1% -> 6.0273973e-05 | W29: =T29*1% -> 6.0273973e-05 | X29: =T29+U29+V29+W29 -> 0.0067506849
A30: RCP-Frsh-00002 | B30: Plates | C30: Frsh | D30: Spinach steak | E30: Saturday | F30: Hot Section | G30: Garnish / By Tray Line | H30: =IFERROR(VLOOKUP(I30,'Raw material list'!$A$3:$C$695,3,0),"") -> PRD1-209 | I30: Fresh Lemon | J30: PC | K30: PC | L30: 10 | M30: =L30/N30*100 -> 26.315789 | N30: 38 | O30: 10 | P30: =IFERROR(L30/O30,0) -> 1 | Q30: =IFERROR(VLOOKUP(I30,'Raw material list'!$A$3:$F$695,6,0),"") -> 0.010088272 | R30: =IFERROR(Q30*P30,0) -> 0.010088272 | S30: =R30*10% -> 0.0010088272 | T30: =R30+S30 -> 0.0110971 | U30: =T30*10% -> 0.00110971 | V30: =T30*1% -> 0.000110971 | W30: =T30*1% -> 0.000110971 | X30: =T30+U30+V30+W30 -> 0.012428752
A31: RCP-Frsh-00002 | B31: Plates | C31: Frsh | D31: Spinach steak | E31: Saturday | F31: Hot Section | G31: Garnish / By Tray Line | H31: =IFERROR(VLOOKUP(I31,'Raw material list'!$A$3:$C$695,3,0),"") -> PRD1-194 | I31: Fresh Chives (Ciboulettes) | J31: Gram | K31: =IFERROR(VLOOKUP(I31,'Raw material list'!$A$3:$E$695,5,0),"") -> Gram | L31: 10 | M31: =L31/N31*100 -> 10.869565 | N31: 92 | O31: 10 | P31: =IFERROR(L31/O31,0) -> 1 | Q31: =IFERROR(VLOOKUP(I31,'Raw material list'!$A$3:$F$695,6,0),"") -> 0.11 | R31: =IFERROR(Q31*P31,0) -> 0.11 | S31: =R31*10% -> 0.011 | T31: =R31+S31 -> 0.121 | U31: =T31*10% -> 0.0121 | V31: =T31*1% -> 0.00121 | W31: =T31*1% -> 0.00121 | X31: =T31+U31+V31+W31 -> 0.13552
A32: RCP-Frsh-00002 | B32: Plates | C32: Frsh | D32: Spinach steak | E32: Saturday | F32: Hot Section | G32: Garnish / By Tray Line | H32: =IFERROR(VLOOKUP(I32,'Raw material list'!$A$3:$C$695,3,0),"") -> PRD3-5038 | I32: Fried Onions | J32: Gram | K32: =IFERROR(VLOOKUP(I32,'Raw material list'!$A$3:$E$695,5,0),"") -> Gram | L32: 50 | M32: =L32/N32*100 -> 50 | N32: 100 | O32: 10 | P32: =IFERROR(L32/O32,0) -> 5 | Q32: =IFERROR(VLOOKUP(I32,'Raw material list'!$A$3:$F$695,6,0),"") -> 0.026 | R32: =IFERROR(Q32*P32,0) -> 0.13 | S32: =R32*10% -> 0.013 | T32: =R32+S32 -> 0.143 | U32: =T32*10% -> 0.0143 | V32: =T32*1% -> 0.00143 | W32: =T32*1% -> 0.00143 | X32: =T32+U32+V32+W32 -> 0.16016
A33: RCP-Frsh-00002 | B33: Plates | C33: Frsh | D33: Spinach steak | E33: Saturday | F33: Hot Section | G33: Spinach Sauce | H33: =IFERROR(VLOOKUP(I33,'Raw material list'!$A$3:$C$695,3,0),"") -> PRD2-363 | I33: Frz Spinach(400 Gram) | J33: Gram | K33: =IFERROR(VLOOKUP(I33,'Raw material list'!$A$3:$E$695,5,0),"") -> Gram | L33: 638.97 | M33: =L33/N33*100 -> 638.97 | N33: 100 | O33: 10 | P33: =IFERROR(L33/O33,0) -> 63.897 | Q33: =IFERROR(VLOOKUP(I33,'Raw material list'!$A$3:$F$695,6,0),"") -> 0.005875 | R33: =IFERROR(Q33*P33,0) -> 0.37539488 | S33: =R33*10% -> 0.037539488 | T33: =R33+S33 -> 0.41293436 | U33: =T33*10% -> 0.041293436 | V33: =T33*1% -> 0.0041293436 | W33: =T33*1% -> 0.0041293436 | X33: =T33+U33+V33+W33 -> 0.46248649
A34: RCP-Frsh-00002 | B34: Plates | C34: Frsh | D34: Spinach steak | E34: Saturday | F34: Hot Section | G34: Spinach Sauce | H34: =IFERROR(VLOOKUP(I34,'Raw material list'!$A$3:$C$695,3,0),"") -> DRY2-1008 | I34: Butter 82% Fat(Unsalted) 25 kg | J34: Gram | K34: =IFERROR(VLOOKUP(I34,'Raw material list'!$A$3:$E$695,5,0),"") -> Gram | L34: 63.89 | M34: =L34/N34*100 -> 63.89 | N34: 100 | O34: 10 | P34: =IFERROR(L34/O34,0) -> 6.389 | Q34: =IFERROR(VLOOKUP(I34,'Raw material list'!$A$3:$F$695,6,0),"") -> 0.038 | R34: =IFERROR(Q34*P34,0) -> 0.242782 | S34: =R34*10% -> 0.0242782 | T34: =R34+S34 -> 0.2670602 | U34: =T34*10% -> 0.02670602 | V34: =T34*1% -> 0.002670602 | W34: =T34*1% -> 0.002670602 | X34: =T34+U34+V34+W34 -> 0.29910742
A35: RCP-Frsh-00002 | B35: Plates | C35: Frsh | D35: Spinach steak | E35: Saturday | F35: Hot Section | G35: Spinach Sauce | H35: =IFERROR(VLOOKUP(I35,'Raw material list'!$A$3:$C$695,3,0),"") -> PRD1-4265 | I35: Fresh onion Yellow(Imported) | J35: Gram | K35: =IFERROR(VLOOKUP(I35,'Raw material list'!$A$3:$E$695,5,0),"") -> Gram | L35: 31.94 | M35: =L35/N35*100 -> 37.576471 | N35: 85 | O35: 10 | P35: =IFERROR(L35/O35,0) -> 3.194 | Q35: =IFERROR(VLOOKUP(I35,'Raw material list'!$A$3:$F$695,6,0),"") -> 0.0035294118 | R35: =IFERROR(Q35*P35,0) -> 0.011272941 | S35: =R35*10% -> 0.0011272941 | T35: =R35+S35 -> 0.012400235 | U35: =T35*10% -> 0.0012400235 | V35: =T35*1% -> 0.00012400235 | W35: =T35*1% -> 0.00012400235 | X35: =T35+U35+V35+W35 -> 0.013888264
A36: RCP-Frsh-00002 | B36: Plates | C36: Frsh | D36: Spinach steak | E36: Saturday | F36: Hot Section | G36: Spinach Sauce | H36: =IFERROR(VLOOKUP(I36,'Raw material list'!$A$3:$C$695,3,0),"") -> PRD1-4327 | I36: Fresh Garlic Peeled | J36: Gram | K36: =IFERROR(VLOOKUP(I36,'Raw material list'!$A$3:$E$695,5,0),"") -> Gram | L36: 3.5 | M36: =L36/N36*100 -> 4.375 | N36: 80 | O36: 10 | P36: =IFERROR(L36/O36,0) -> 0.35 | Q36: =IFERROR(VLOOKUP(I36,'Raw material list'!$A$3:$F$695,6,0),"") -> 0.013 | R36: =IFERROR(Q36*P36,0) -> 0.00455 | S36: =R36*10% -> 0.000455 | T36: =R36+S36 -> 0.005005 | U36: =T36*10% -> 0.0005005 | V36: =T36*1% -> 5.005e-05 | W36: =T36*1% -> 5.005e-05 | X36: =T36+U36+V36+W36 -> 0.0056056
A37: RCP-Frsh-00002 | B37: Plates | C37: Frsh | D37: Spinach steak | E37: Saturday | F37: Hot Section | G37: Spinach Sauce | H37: =IFERROR(VLOOKUP(I37,'Raw material list'!$A$3:$C$695,3,0),"") -> DRS5-980 | I37: Flour Cake Special (all purpose) | J37: Gram | K37: =IFERROR(VLOOKUP(I37,'Raw material list'!$A$3:$E$695,5,0),"") -> Gram | L37: 12.77 | M37: =L37/N37*100 -> 12.77 | N37: 100 | O37: 10 | P37: =IFERROR(L37/O37,0) -> 1.277 | Q37: =IFERROR(VLOOKUP(I37,'Raw material list'!$A$3:$F$695,6,0),"") -> 0.001 | R37: =IFERROR(Q37*P37,0) -> 0.001277 | S37: =R37*10% -> 0.0001277 | T37: =R37+S37 -> 0.0014047 | U37: =T37*10% -> 0.00014047 | V37: =T37*1% -> 1.4047e-05 | W37: =T37*1% -> 1.4047e-05 | X37: =T37+U37+V37+W37 -> 0.001573264
A38: RCP-Frsh-00002 | B38: Plates | C38: Frsh | D38: Spinach steak | E38: Saturday | F38: Hot Section | G38: Spinach Sauce | H38: =IFERROR(VLOOKUP(I38,'Raw material list'!$A$3:$C$695,3,0),"") -> DRY2-1858 | I38: Cooking Cream 1 Ltr | J38: Ml | K38: =IFERROR(VLOOKUP(I38,'Raw material list'!$A$3:$E$695,5,0),"") -> Ml | L38: 798.72 | M38: =L38/N38*100 -> 798.72 | N38: 100 | O38: 10 | P38: =IFERROR(L38/O38,0) -> 79.872 | Q38: =IFERROR(VLOOKUP(I38,'Raw material list'!$A$3:$F$695,6,0),"") -> 0.00988 | R38: =IFERROR(Q38*P38,0) -> 0.78913536 | S38: =R38*10% -> 0.078913536 | T38: =R38+S38 -> 0.8680489 | U38: =T38*10% -> 0.08680489 | V38: =T38*1% -> 0.008680489 | W38: =T38*1% -> 0.008680489 | X38: =T38+U38+V38+W38 -> 0.97221476
A39: RCP-Frsh-00002 | B39: Plates | C39: Frsh | D39: Spinach steak | E39: Saturday | F39: Hot Section | G39: Spinach Sauce | H39: =IFERROR(VLOOKUP(I39,'Raw material list'!$A$3:$C$695,3,0),"") -> DRS1-114 | I39: Sea Salt(737 Gram) | J39: Gram | K39: =IFERROR(VLOOKUP(I39,'Raw material list'!$A$3:$E$695,5,0),"") -> Gram | L39: 3.99 | M39: =L39/N39*100 -> 3.99 | N39: 100 | O39: 10 | P39: =IFERROR(L39/O39,0) -> 0.399 | Q39: =IFERROR(VLOOKUP(I39,'Raw material list'!$A$3:$F$695,6,0),"") -> 0.0047489824 | R39: =IFERROR(Q39*P39,0) -> 0.001894844 | S39: =R39*10% -> 0.0001894844 | T39: =R39+S39 -> 0.0020843284 | U39: =T39*10% -> 0.00020843284 | V39: =T39*1% -> 2.0843284e-05 | W39: =T39*1% -> 2.0843284e-05 | X39: =T39+U39+V39+W39 -> 0.0023344478
A40: RCP-Frsh-00002 | B40: Plates | C40: Frsh | D40: Spinach steak | E40: Saturday | F40: Hot Section | G40: Spinach Sauce | H40: =IFERROR(VLOOKUP(I40,'Raw material list'!$A$3:$C$695,3,0),"") -> DRS6-537 | I40: Spices Pepper Black Powder(1 Kg) | J40: Gram | K40: =IFERROR(VLOOKUP(I40,'Raw material list'!$A$3:$E$695,5,0),"") -> Gram | L40: 2.39 | M40: =L40/N40*100 -> 2.39 | N40: 100 | O40: 10 | P40: =IFERROR(L40/O40,0) -> 0.239 | Q40: =IFERROR(VLOOKUP(I40,'Raw material list'!$A$3:$F$695,6,0),"") -> 0.035 | R40: =IFERROR(Q40*P40,0) -> 0.008365 | S40: =R40*10% -> 0.0008365 | T40: =R40+S40 -> 0.0092015 | U40: =T40*10% -> 0.00092015 | V40: =T40*1% -> 9.2015e-05 | W40: =T40*1% -> 9.2015e-05 | X40: =T40+U40+V40+W40 -> 0.01030568
A41: RCP-Frsh-00002 | B41: Plates | C41: Frsh | D41: Spinach steak | E41: Saturday | F41: Hot Section | G41: Spinach Sauce | H41: =IFERROR(VLOOKUP(I41,'Raw material list'!$A$3:$C$695,3,0),"") -> PRD1-209 | I41: Fresh Lemon | J41: Gram | K41: =IFERROR(VLOOKUP(I41,'Raw material list'!$A$3:$E$695,5,0),"") -> Gram | L41: 3.19 | M41: =L41/N41*100 -> 8.3947368 | N41: 38 | O41: 10 | P41: =IFERROR(L41/O41,0) -> 0.319 | Q41: =IFERROR(VLOOKUP(I41,'Raw material list'!$A$3:$F$695,6,0),"") -> 0.010088272 | R41: =IFERROR(Q41*P41,0) -> 0.0032181589 | S41: =R41*10% -> 0.00032181589 | T41: =R41+S41 -> 0.0035399748 | U41: =T41*10% -> 0.00035399748 | V41: =T41*1% -> 3.5399748e-05 | W41: =T41*1% -> 3.5399748e-05 | X41: =T41+U41+V41+W41 -> 0.0039647718
A42: RCP-Frsh-00002 | B42: Plates | C42: Frsh | D42: Spinach steak | E42: Saturday | F42: Hot Section | G42: White Rice | H42: =IFERROR(VLOOKUP(I42,'Raw material list'!$A$3:$C$695,3,0),"") -> DRS4-498 | I42: Rice Basmati | J42: Gram | K42: =IFERROR(VLOOKUP(I42,'Raw material list'!$A$3:$E$695,5,0),"") -> Gram | L42: 600 | M42: =L42/N42*100 -> 600 | N42: 100 | O42: 10 | P42: =IFERROR(L42/O42,0) -> 60 | Q42: =IFERROR(VLOOKUP(I42,'Raw material list'!$A$3:$F$695,6,0),"") -> 0.00575 | R42: =IFERROR(Q42*P42,0) -> 0.345 | S42: =R42*10% -> 0.0345 | T42: =R42+S42 -> 0.3795 | U42: =T42*10% -> 0.03795 | V42: =T42*1% -> 0.003795 | W42: =T42*1% -> 0.003795 | X42: =T42+U42+V42+W42 -> 0.42504
... A49: RCP-Frsh-00002 | B49: Plates | C49: Frsh | D49: Spinach steak | E49: Saturday | F49: Hot Section | G49: White Rice | H49: =IFERROR(VLOOKUP(I49,'Raw material list'!$A$3:$C$695,3,0),"") -> DRS6-261 | I49: Cinnamon Stick | J49: Gram | K49: =IFERROR(VLOOKUP(I49,'Raw material list'!$A$3:$E$695,5,0),"") -> Gram | L49: 0.3 | M49: =L49/N49*100 -> 0.3 | N49: 100 | O49: 10 | P49: =IFERROR(L49/O49,0) -> 0.03 | Q49: =IFERROR(VLOOKUP(I49,'Raw material list'!$A$3:$F$695,6,0),"") -> 0.014 | R49: =IFERROR(Q49*P49,0) -> 0.00042 | S49: =R49*10% -> 4.2e-05 | T49: =R49+S49 -> 0.000462 | U49: =T49*10% -> 4.62e-05 | V49: =T49*1% -> 4.62e-06 | W49: =T49*1% -> 4.62e-06 | X49: =T49+U49+V49+W49 -> 0.00051744
A50: RCP-Frsh-00003 | B50: Plates | C50: Frsh | D50: Misto chicken broccoli | E50: Saturday, Monday | F50: Butchery Section | G50: Marinated chicken: | H50: =IFERROR(VLOOKUP(I50,'Raw material list'!$A$3:$C$695,3,0),"") -> PLT2-3278 | I50: Frz Chicken Breast Tender (KG) | J50: Gram | K50: =IFERROR(VLOOKUP(I50,'Raw material list'!$A$3:$E$695,5,0),"") -> Gram | L50: 1200 | M50: =L50/N50*100 -> 1574.8031 | N50: 76.2 | O50: 10 | P50: =IFERROR(L50/O50,0) -> 120 | Q50: =IFERROR(VLOOKUP(I50,'Raw material list'!$A$3:$F$695,6,0),"") -> 0.030357143 | R50: =IFERROR(Q50*P50,0) -> 3.6428571 | S50: =R50*10% -> 0.36428571 | T50: =R50+S50 -> 4.0071429 | U50: =T50*10% -> 0.40071429 | V50: =T50*1% -> 0.040071429 | W50: =T50*1% -> 0.040071429 | X50: =T50+U50+V50+W50 -> 4.488 | Y50: Chicken Breast Butterfly - 140 g
A51: RCP-Frsh-00003 | B51: Plates | C51: Frsh | D51: Misto chicken broccoli | E51: Saturday, Monday | F51: Butchery Section | G51: Marinated chicken: | H51: =IFERROR(VLOOKUP(I51,'Raw material list'!$A$3:$C$695,3,0),"") -> DRS6-1727 | I51: Spice Paprika Sweet (KG) | J51: Gram | K51: =IFERROR(VLOOKUP(I51,'Raw material list'!$A$3:$E$695,5,0),"") -> Gram | L51: 12 | M51: =L51/N51*100 -> 12 | N51: 100 | O51: 10 | P51: =IFERROR(L51/O51,0) -> 1.2 | Q51: =IFERROR(VLOOKUP(I51,'Raw material list'!$A$3:$F$695,6,0),"") -> 0.025 | R51: =IFERROR(Q51*P51,0) -> 0.03 | S51: =R51*10% -> 0.003 | T51: =R51+S51 -> 0.033 | U51: =T51*10% -> 0.0033 | V51: =T51*1% -> 0.00033 | W51: =T51*1% -> 0.00033 | X51: =T51+U51+V51+W51 -> 0.03696
A52: RCP-Frsh-00003 | B52: Plates | C52: Frsh | D52: Misto chicken broccoli | E52: Saturday, Monday | F52: Butchery Section | G52: Marinated chicken: | H52: =IFERROR(VLOOKUP(I52,'Raw material list'!$A$3:$C$695,3,0),"") -> DRS6-5088 | I52: Spice Cajun (2 Kg) | J52: Gram | K52: =IFERROR(VLOOKUP(I52,'Raw material list'!$A$3:$E$695,5,0),"") -> Gram | L52: 12 | M52: =L52/N52*100 -> 12 | N52: 100 | O52: 10 | P52: =IFERROR(L52/O52,0) -> 1.2 | Q52: =IFERROR(VLOOKUP(I52,'Raw material list'!$A$3:$F$695,6,0),"") -> 0.08 | R52: =IFERROR(Q52*P52,0) -> 0.096 | S52: =R52*10% -> 0.0096 | T52: =R52+S52 -> 0.1056 | U52: =T52*10% -> 0.01056 | V52: =T52*1% -> 0.001056 | W52: =T52*1% -> 0.001056 | X52: =T52+U52+V52+W52 -> 0.118272
A53: RCP-Frsh-00003 | B53: Plates | C53: Frsh | D53: Misto chicken broccoli | E53: Saturday, Monday | F53: Butchery Section | G53: Marinated chicken: | H53: =IFERROR(VLOOKUP(I53,'Raw material list'!$A$3:$C$695,3,0),"") -> DRS6-5376 | I53: Dry Thyme 500gm | J53: Gram | K53: =IFERROR(VLOOKUP(I53,'Raw material list'!$A$3:$E$695,5,0),"") -> Gram | L53: 3 | M53: =L53/N53*100 -> 3 | N53: 100 | O53: 10 | P53: =IFERROR(L53/O53,0) -> 0.3 | Q53: =IFERROR(VLOOKUP(I53,'Raw material list'!$A$3:$F$695,6,0),"") -> 0.028 | R53: =IFERROR(Q53*P53,0) -> 0.0084 | S53: =R53*10% -> 0.00084 | T53: =R53+S53 -> 0.00924 | U53: =T53*10% -> 0.000924 | V53: =T53*1% -> 9.24e-05 | W53: =T53*1% -> 9.24e-05 | X53: =T53+U53+V53+W53 -> 0.0103488
A54: RCP-Frsh-00003 | B54: Plates | C54: Frsh | D54: Misto chicken broccoli | E54: Saturday, Monday | F54: Butchery Section | G54: Marinated chicken: | H54: =IFERROR(VLOOKUP(I54,'Raw material list'!$A$3:$C$695,3,0),"") -> WAT-001 | I54: Tap Water-cooking | J54: Ml | K54: =IFERROR(VLOOKUP(I54,'Raw material list'!$A$3:$E$695,5,0),"") -> Ml | L54: 120 | M54: =L54/N54*100 -> 120 | N54: 100 | O54: 10 | P54: =IFERROR(L54/O54,0) -> 12 | Q54: =IFERROR(VLOOKUP(I54,'Raw material list'!$A$3:$F$695,6,0),"") -> 8e-05 | R54: =IFERROR(Q54*P54,0) -> 0.00096 | S54: =R54*10% -> 9.6e-05 | T54: =R54+S54 -> 0.001056 | U54: =T54*10% -> 0.0001056 | V54: =T54*1% -> 1.056e-05 | W54: =T54*1% -> 1.056e-05 | X54: =T54+U54+V54+W54 -> 0.00118272
A55: RCP-Frsh-00003 | B55: Plates | C55: Frsh | D55: Misto chicken broccoli | E55: Saturday, Monday | F55: Hot Section | G55: Garnish / Kitchen | H55: =IFERROR(VLOOKUP(I55,'Raw material list'!$A$3:$C$695,3,0),"") -> PRD1-182 | I55: Fresh Brocoli | J55: Gram | K55: =IFERROR(VLOOKUP(I55,'Raw material list'!$A$3:$E$695,5,0),"") -> Gram | L55: 50 | M55: =L55/N55*100 -> 63.559322 | N55: 78.666667 | O55: 10 | P55: =IFERROR(L55/O55,0) -> 5 | Q55: =IFERROR(VLOOKUP(I55,'Raw material list'!$A$3:$F$695,6,0),"") -> 0.017789072 | R55: =IFERROR(Q55*P55,0) -> 0.088945362 | S55: =R55*10% -> 0.0088945362 | T55: =R55+S55 -> 0.097839898 | U55: =T55*10% -> 0.0097839898 | V55: =T55*1% -> 0.00097839898 | W55: =T55*1% -> 0.00097839898 | X55: =T55+U55+V55+W55 -> 0.10958069
A56: RCP-Frsh-00003 | B56: Plates | C56: Frsh | D56: Misto chicken broccoli | E56: Saturday, Monday | F56: Hot Section | G56: Broccoli Sauce | H56: =IFERROR(VLOOKUP(I56,'Raw material list'!$A$3:$C$695,3,0),"") -> PRD1-182 | I56: Fresh Brocoli | J56: Gram | K56: =IFERROR(VLOOKUP(I56,'Raw material list'!$A$3:$E$695,5,0),"") -> Gram | L56: 328.76 | M56: =L56/N56*100 -> 417.91525 | N56: 78.666667 | O56: 10 | P56: =IFERROR(L56/O56,0) -> 32.876 | Q56: =IFERROR(VLOOKUP(I56,'Raw material list'!$A$3:$F$695,6,0),"") -> 0.017789072 | R56: =IFERROR(Q56*P56,0) -> 0.58483355 | S56: =R56*10% -> 0.058483355 | T56: =R56+S56 -> 0.6433169 | U56: =T56*10% -> 0.06433169 | V56: =T56*1% -> 0.006433169 | W56: =T56*1% -> 0.006433169 | X56: =T56+U56+V56+W56 -> 0.72051493
A57: RCP-Frsh-00003 | B57: Plates | C57: Frsh | D57: Misto chicken broccoli | E57: Saturday, Monday | F57: Hot Section | G57: Broccoli Sauce | H57: =IFERROR(VLOOKUP(I57,'Raw material list'!$A$3:$C$695,3,0),"") -> PRD1-4327 | I57: Fresh Garlic Peeled | J57: Gram | K57: =IFERROR(VLOOKUP(I57,'Raw material list'!$A$3:$E$695,5,0),"") -> Gram | L57: 4.04 | M57: =L57/N57*100 -> 5.05 | N57: 80 | O57: 10 | P57: =IFERROR(L57/O57,0) -> 0.404 | Q57: =IFERROR(VLOOKUP(I57,'Raw material list'!$A$3:$F$695,6,0),"") -> 0.013 | R57: =IFERROR(Q57*P57,0) -> 0.005252 | S57: =R57*10% -> 0.0005252 | T57: =R57+S57 -> 0.0057772 | U57: =T57*10% -> 0.00057772 | V57: =T57*1% -> 5.7772e-05 | W57: =T57*1% -> 5.7772e-05 | X57: =T57+U57+V57+W57 -> 0.006470464
A58: RCP-Frsh-00003 | B58: Plates | C58: Frsh | D58: Misto chicken broccoli | E58: Saturday, Monday | F58: Hot Section | G58: Broccoli Sauce | H58: =IFERROR(VLOOKUP(I58,'Raw material list'!$A$3:$C$695,3,0),"") -> DRS3-1615 | I58: Olive Oil (CAN) | J58: Ml | K58: =IFERROR(VLOOKUP(I58,'Raw material list'!$A$3:$E$695,5,0),"") -> Ml | L58: 22.83 | M58: =L58/N58*100 -> 22.83 | N58: 100 | O58: 10 | P58: =IFERROR(L58/O58,0) -> 2.283 | Q58: =IFERROR(VLOOKUP(I58,'Raw material list'!$A$3:$F$695,6,0),"") -> 0.012 | R58: =IFERROR(Q58*P58,0) -> 0.027396 | S58: =R58*10% -> 0.0027396 | T58: =R58+S58 -> 0.0301356 | U58: =T58*10% -> 0.00301356 | V58: =T58*1% -> 0.000301356 | W58: =T58*1% -> 0.000301356 | X58: =T58+U58+V58+W58 -> 0.033751872
A59: RCP-Frsh-00003 | B59: Plates | C59: Frsh | D59: Misto chicken broccoli | E59: Saturday, Monday | F59: Hot Section | G59: Broccoli Sauce | H59: =IFERROR(VLOOKUP(I59,'Raw material list'!$A$3:$C$695,3,0),"") -> DRS1-114 | I59: Sea Salt(737 Gram) | J59: Gram | K59: =IFERROR(VLOOKUP(I59,'Raw material list'!$A$3:$E$695,5,0),"") -> Gram | L59: 11.51 | M59: =L59/N59*100 -> 11.51 | N59: 100 | O59: 10 | P59: =IFERROR(L59/O59,0) -> 1.151 | Q59: =IFERROR(VLOOKUP(I59,'Raw material list'!$A$3:$F$695,6,0),"") -> 0.0047489824 | R59: =IFERROR(Q59*P59,0) -> 0.0054660787 | S59: =R59*10% -> 0.00054660787 | T59: =R59+S59 -> 0.0060126866 | U59: =T59*10% -> 0.00060126866 | V59: =T59*1% -> 6.0126866e-05 | W59: =T59*1% -> 6.0126866e-05 | X59: =T59+U59+V59+W59 -> 0.006734209
A60: RCP-Frsh-00003 | B60: Plates | C60: Frsh | D60: Misto chicken broccoli | E60: Saturday, Monday | F60: Hot Section | G60: Broccoli Sauce | H60: =IFERROR(VLOOKUP(I60,'Raw material list'!$A$3:$C$695,3,0),"") -> DRS6-537 | I60: Spices Pepper Black Powder(1 Kg) | J60: Gram | K60: =IFERROR(VLOOKUP(I60,'Raw material list'!$A$3:$E$695,5,0),"") -> Gram | L60: 6.3 | M60: =L60/N60*100 -> 6.3 | N60: 100 | O60: 10 | P60: =IFERROR(L60/O60,0) -> 0.63 | Q60: =IFERROR(VLOOKUP(I60,'Raw material list'!$A$3:$F$695,6,0),"") -> 0.035 | R60: =IFERROR(Q60*P60,0) -> 0.02205 | S60: =R60*10% -> 0.002205 | T60: =R60+S60 -> 0.024255 | U60: =T60*10% -> 0.0024255 | V60: =T60*1% -> 0.00024255 | W60: =T60*1% -> 0.00024255 | X60: =T60+U60+V60+W60 -> 0.0271656
A61: RCP-Frsh-00003 | B61: Plates | C61: Frsh | D61: Misto chicken broccoli | E61: Saturday, Monday | F61: Hot Section | G61: Broccoli Sauce | H61: =IFERROR(VLOOKUP(I61,'Raw material list'!$A$3:$C$695,3,0),"") -> DRY2-1858 | I61: Cooking Cream 1 Ltr | J61: Ml | K61: =IFERROR(VLOOKUP(I61,'Raw material list'!$A$3:$E$695,5,0),"") -> Ml | L61: 637.05 | M61: =L61/N61*100 -> 637.05 | N61: 100 | O61: 10 | P61: =IFERROR(L61/O61,0) -> 63.705 | Q61: =IFERROR(VLOOKUP(I61,'Raw material list'!$A$3:$F$695,6,0),"") -> 0.00988 | R61: =IFERROR(Q61*P61,0) -> 0.6294054 | S61: =R61*10% -> 0.06294054 | T61: =R61+S61 -> 0.69234594 | U61: =T61*10% -> 0.069234594 | V61: =T61*1% -> 0.0069234594 | W61: =T61*1% -> 0.0069234594 | X61: =T61+U61+V61+W61 -> 0.77542745
A62: RCP-Frsh-00003 | B62: Plates | C62: Frsh | D62: Misto chicken broccoli | E62: Saturday, Monday | F62: Hot Section | G62: Broccoli Sauce | H62: =IFERROR(VLOOKUP(I62,'Raw material list'!$A$3:$C$695,3,0),"") -> DRY1-602 | I62: Cheese Parmesan Grated | J62: Gram | K62: =IFERROR(VLOOKUP(I62,'Raw material list'!$A$3:$E$695,5,0),"") -> Gram | L62: 43.05 | M62: =L62/N62*100 -> 43.05 | N62: 100 | O62: 10 | P62: =IFERROR(L62/O62,0) -> 4.305 | Q62: =IFERROR(VLOOKUP(I62,'Raw material list'!$A$3:$F$695,6,0),"") -> 0.055 | R62: =IFERROR(Q62*P62,0) -> 0.236775 | S62: =R62*10% -> 0.0236775 | T62: =R62+S62 -> 0.2604525 | U62: =T62*10% -> 0.02604525 | V62: =T62*1% -> 0.002604525 | W62: =T62*1% -> 0.002604525 | X62: =T62+U62+V62+W62 -> 0.2917068
... A71: RCP-Frsh-00003 | B71: Plates | C71: Frsh | D71: Misto chicken broccoli | E71: Saturday, Monday | F71: Hot Section | G71: White Rice | H71: =IFERROR(VLOOKUP(I71,'Raw material list'!$A$3:$C$695,3,0),"") -> DRS6-261 | I71: Cinnamon Stick | J71: Gram | K71: =IFERROR(VLOOKUP(I71,'Raw material list'!$A$3:$E$695,5,0),"") -> Gram | L71: 0.3 | M71: =L71/N71*100 -> 0.3 | N71: 100 | O71: 10 | P71: =IFERROR(L71/O71,0) -> 0.03 | Q71: =IFERROR(VLOOKUP(I71,'Raw material list'!$A$3:$F$695,6,0),"") -> 0.014 | R71: =IFERROR(Q71*P71,0) -> 0.00042 | S71: =R71*10% -> 4.2e-05 | T71: =R71+S71 -> 0.000462 | U71: =T71*10% -> 4.62e-05 | V71: =T71*1% -> 4.62e-06 | W71: =T71*1% -> 4.62e-06 | X71: =T71+U71+V71+W71 -> 0.00051744
A72: RCP-Frsh-00004 | B72: Sandwiches | C72: Frsh | D72: Honey Pecan Halloumi | E72: Saturday,Tuesday | F72: TrayLine Section | H72: =IFERROR(VLOOKUP(I72,'Raw material list'!$A$3:$C$695,3,0),"") -> BKR1-1327 | I72: Bread Sliced Brown Med-400001 | J72: Slice | K72: =IFERROR(VLOOKUP(I72,'Raw material list'!$A$3:$E$695,5,0),"") -> Slice | L72: 10 | M72: =L72/N72*100 -> 10 | N72: 100 | O72: 10 | P72: =IFERROR(L72/O72,0) -> 1 | Q72: =IFERROR(VLOOKUP(I72,'Raw material list'!$A$3:$F$695,6,0),"") -> 0.22222222 | R72: =IFERROR(Q72*P72,0) -> 0.22222222 | S72: =R72*10% -> 0.022222222 | T72: =R72+S72 -> 0.24444444 | U72: =T72*10% -> 0.024444444 | V72: =T72*1% -> 0.0024444444 | W72: =T72*1% -> 0.0024444444 | X72: =T72+U72+V72+W72 -> 0.27377778
A73: RCP-Frsh-00004 | B73: Sandwiches | C73: Frsh | D73: Honey Pecan Halloumi | E73: Saturday,Tuesday | F73: Hot Section | H73: =IFERROR(VLOOKUP(I73,'Raw material list'!$A$3:$C$695,3,0),"") -> DRY1-353 | I73: Halloumi | J73: Gram | K73: =IFERROR(VLOOKUP(I73,'Raw material list'!$A$3:$E$695,5,0),"") -> Gram | L73: 700 | M73: =L73/N73*100 -> 700 | N73: 100 | O73: 10 | P73: =IFERROR(L73/O73,0) -> 70 | Q73: =IFERROR(VLOOKUP(I73,'Raw material list'!$A$3:$F$695,6,0),"") -> 0.0245 | R73: =IFERROR(Q73*P73,0) -> 1.715 | S73: =R73*10% -> 0.1715 | T73: =R73+S73 -> 1.8865 | U73: =T73*10% -> 0.18865 | V73: =T73*1% -> 0.018865 | W73: =T73*1% -> 0.018865 | X73: =T73+U73+V73+W73 -> 2.11288
A74: RCP-Frsh-00004 | B74: Sandwiches | C74: Frsh | D74: Honey Pecan Halloumi | E74: Saturday,Tuesday | F74: Hot Section | G74: Sauce | H74: =IFERROR(VLOOKUP(I74,'Raw material list'!$A$3:$C$695,3,0),"") -> DRS1-1780 | I74: Honey Jar (3 KG) | J74: Gram | K74: =IFERROR(VLOOKUP(I74,'Raw material list'!$A$3:$E$695,5,0),"") -> Gram | L74: 150 | M74: =L74/N74*100 -> 150 | N74: 100 | O74: 10 | P74: =IFERROR(L74/O74,0) -> 15 | Q74: =IFERROR(VLOOKUP(I74,'Raw material list'!$A$3:$F$695,6,0),"") -> 0.04 | R74: =IFERROR(Q74*P74,0) -> 0.6 | S74: =R74*10% -> 0.06 | T74: =R74+S74 -> 0.66 | U74: =T74*10% -> 0.066 | V74: =T74*1% -> 0.0066 | W74: =T74*1% -> 0.0066 | X74: =T74+U74+V74+W74 -> 0.7392
A75: RCP-Frsh-00004 | B75: Sandwiches | C75: Frsh | D75: Honey Pecan Halloumi | E75: Saturday,Tuesday | F75: TrayLine Section | G75: Garnish | H75: =IFERROR(VLOOKUP(I75,'Raw material list'!$A$3:$C$695,3,0),"") | I75: Caramelized Pecan | K75: =IFERROR(VLOOKUP(I75,'Raw material list'!$A$3:$E$695,5,0),"") | L75: 50 | M75: =L75/N75*100 -> 50 | N75: 100 | O75: 10 | P75: =IFERROR(L75/O75,0) -> 5 | Q75: =IFERROR(VLOOKUP(I75,'Raw material list'!$A$3:$F$695,6,0),"") | R75: =IFERROR(Q75*P75,0) -> 0 | S75: =R75*10% -> 0 | T75: =R75+S75 -> 0 | U75: =T75*10% -> 0 | V75: =T75*1% -> 0 | W75: =T75*1% -> 0 | X75: =T75+U75+V75+W75 -> 0
A76: RCP-Frsh-00005 | B76: Plates | C76: Frsh | D76: Pasta Creamy Potato | E76: Saturday | F76: Butchery Section | G76: Marinated chicken: | H76: =IFERROR(VLOOKUP(I76,'Raw material list'!$A$3:$C$695,3,0),"") -> PLT2-3278 | I76: Frz Chicken Breast Tender (KG) | J76: Gram | K76: =IFERROR(VLOOKUP(I76,'Raw material list'!$A$3:$E$695,5,0),"") -> Gram | L76: 1400 | M76: =L76/N76*100 -> 1837.2703 | N76: 76.2 | O76: 10 | P76: =IFERROR(L76/O76,0) -> 140 | Q76: =IFERROR(VLOOKUP(I76,'Raw material list'!$A$3:$F$695,6,0),"") -> 0.030357143 | R76: =IFERROR(Q76*P76,0) -> 4.25 | S76: =R76*10% -> 0.425 | T76: =R76+S76 -> 4.675 | U76: =T76*10% -> 0.4675 | V76: =T76*1% -> 0.04675 | W76: =T76*1% -> 0.04675 | X76: =T76+U76+V76+W76 -> 5.236 | Y76: Chicken Breast Butterfly - 140 g
A77: RCP-Frsh-00005 | B77: Plates | C77: Frsh | D77: Pasta Creamy Potato | E77: Saturday | F77: Butchery Section | G77: Marinated chicken: | H77: =IFERROR(VLOOKUP(I77,'Raw material list'!$A$3:$C$695,3,0),"") -> DRS6-1727 | I77: Spice Paprika Sweet (KG) | J77: Gram | K77: =IFERROR(VLOOKUP(I77,'Raw material list'!$A$3:$E$695,5,0),"") -> Gram | L77: 12 | M77: =L77/N77*100 -> 12 | N77: 100 | O77: 10 | P77: =IFERROR(L77/O77,0) -> 1.2 | Q77: =IFERROR(VLOOKUP(I77,'Raw material list'!$A$3:$F$695,6,0),"") -> 0.025 | R77: =IFERROR(Q77*P77,0) -> 0.03 | S77: =R77*10% -> 0.003 | T77: =R77+S77 -> 0.033 | U77: =T77*10% -> 0.0033 | V77: =T77*1% -> 0.00033 | W77: =T77*1% -> 0.00033 | X77: =T77+U77+V77+W77 -> 0.03696
A78: RCP-Frsh-00005 | B78: Plates | C78: Frsh | D78: Pasta Creamy Potato | E78: Saturday | F78: Butchery Section | G78: Marinated chicken: | H78: =IFERROR(VLOOKUP(I78,'Raw material list'!$A$3:$C$695,3,0),"") -> DRS6-5088 | I78: Spice Cajun (2 Kg) | J78: Gram | K78: =IFERROR(VLOOKUP(I78,'Raw material list'!$A$3:$E$695,5,0),"") -> Gram | L78: 12 | M78: =L78/N78*100 -> 12 | N78: 100 | O78: 10 | P78: =IFERROR(L78/O78,0) -> 1.2 | Q78: =IFERROR(VLOOKUP(I78,'Raw material list'!$A$3:$F$695,6,0),"") -> 0.08 | R78: =IFERROR(Q78*P78,0) -> 0.096 | S78: =R78*10% -> 0.0096 | T78: =R78+S78 -> 0.1056 | U78: =T78*10% -> 0.01056 | V78: =T78*1% -> 0.001056 | W78: =T78*1% -> 0.001056 | X78: =T78+U78+V78+W78 -> 0.118272
A79: RCP-Frsh-00005 | B79: Plates | C79: Frsh | D79: Pasta Creamy Potato | E79: Saturday | F79: Butchery Section | G79: Marinated chicken: | H79: =IFERROR(VLOOKUP(I79,'Raw material list'!$A$3:$C$695,3,0),"") -> DRS6-5376 | I79: Dry Thyme 500gm | J79: Gram | K79: =IFERROR(VLOOKUP(I79,'Raw material list'!$A$3:$E$695,5,0),"") -> Gram | L79: 3 | M79: =L79/N79*100 -> 3 | N79: 100 | O79: 10 | P79: =IFERROR(L79/O79,0) -> 0.3 | Q79: =IFERROR(VLOOKUP(I79,'Raw material list'!$A$3:$F$695,6,0),"") -> 0.028 | R79: =IFERROR(Q79*P79,0) -> 0.0084 | S79: =R79*10% -> 0.00084 | T79: =R79+S79 -> 0.00924 | U79: =T79*10% -> 0.000924 | V79: =T79*1% -> 9.24e-05 | W79: =T79*1% -> 9.24e-05 | X79: =T79+U79+V79+W79 -> 0.0103488
A80: RCP-Frsh-00005 | B80: Plates | C80: Frsh | D80: Pasta Creamy Potato | E80: Saturday | F80: Butchery Section | G80: Marinated chicken: | H80: =IFERROR(VLOOKUP(I80,'Raw material list'!$A$3:$C$695,3,0),"") -> WAT-001 | I80: Tap Water-cooking | J80: Ml | K80: =IFERROR(VLOOKUP(I80,'Raw material list'!$A$3:$E$695,5,0),"") -> Ml | L80: 120 | M80: =L80/N80*100 -> 120 | N80: 100 | O80: 10 | P80: =IFERROR(L80/O80,0) -> 12 | Q80: =IFERROR(VLOOKUP(I80,'Raw material list'!$A$3:$F$695,6,0),"") -> 8e-05 | R80: =IFERROR(Q80*P80,0) -> 0.00096 | S80: =R80*10% -> 9.6e-05 | T80: =R80+S80 -> 0.001056 | U80: =T80*10% -> 0.0001056 | V80: =T80*1% -> 1.056e-05 | W80: =T80*1% -> 1.056e-05 | X80: =T80+U80+V80+W80 -> 0.00118272
A81: RCP-Frsh-00005 | B81: Plates | C81: Frsh | D81: Pasta Creamy Potato | E81: Saturday | F81: Hot Section | H81: =IFERROR(VLOOKUP(I81,'Raw material list'!$A$3:$C$695,3,0),"") -> DRS2-4321 | I81: Pasta Penne Rigate (1 Kg) | J81: Gram | K81: =IFERROR(VLOOKUP(I81,'Raw material list'!$A$3:$E$695,5,0),"") -> Gram | L81: 700 | M81: =L81/N81*100 -> 700 | N81: 100 | O81: 10 | P81: =IFERROR(L81/O81,0) -> 70 | Q81: =IFERROR(VLOOKUP(I81,'Raw material list'!$A$3:$F$695,6,0),"") -> 0.00803 | R81: =IFERROR(Q81*P81,0) -> 0.5621 | S81: =R81*10% -> 0.05621 | T81: =R81+S81 -> 0.61831 | U81: =T81*10% -> 0.061831 | V81: =T81*1% -> 0.0061831 | W81: =T81*1% -> 0.0061831 | X81: =T81+U81+V81+W81 -> 0.6925072
A82: RCP-Frsh-00005 | B82: Plates | C82: Frsh | D82: Pasta Creamy Potato | E82: Saturday | F82: Hot Section | G82: Garnish / Tray Line | H82: =IFERROR(VLOOKUP(I82,'Raw material list'!$A$3:$C$695,3,0),"") -> DRY2-1008 | I82: Butter 82% Fat(Unsalted) 25 kg | J82: Gram | K82: =IFERROR(VLOOKUP(I82,'Raw material list'!$A$3:$E$695,5,0),"") -> Gram | L82: 30 | M82: =L82/N82*100 -> 30 | N82: 100 | O82: 10 | P82: =IFERROR(L82/O82,0) -> 3 | Q82: =IFERROR(VLOOKUP(I82,'Raw material list'!$A$3:$F$695,6,0),"") -> 0.038 | R82: =IFERROR(Q82*P82,0) -> 0.114 | S82: =R82*10% -> 0.0114 | T82: =R82+S82 -> 0.1254 | U82: =T82*10% -> 0.01254 | V82: =T82*1% -> 0.001254 | W82: =T82*1% -> 0.001254 | X82: =T82+U82+V82+W82 -> 0.140448
A83: RCP-Frsh-00005 | B83: Plates | C83: Frsh | D83: Pasta Creamy Potato | E83: Saturday | F83: Hot Section | G83: Garnish / Tray Line | H83: =IFERROR(VLOOKUP(I83,'Raw material list'!$A$3:$C$695,3,0),"") -> PRD1-194 | I83: Fresh Chives (Ciboulettes) | J83: Gram | K83: =IFERROR(VLOOKUP(I83,'Raw material list'!$A$3:$E$695,5,0),"") -> Gram | L83: 10 | M83: =L83/N83*100 -> 10.869565 | N83: 92 | O83: 10 | P83: =IFERROR(L83/O83,0) -> 1 | Q83: =IFERROR(VLOOKUP(I83,'Raw material list'!$A$3:$F$695,6,0),"") -> 0.11 | R83: =IFERROR(Q83*P83,0) -> 0.11 | S83: =R83*10% -> 0.011 | T83: =R83+S83 -> 0.121 | U83: =T83*10% -> 0.0121 | V83: =T83*1% -> 0.00121 | W83: =T83*1% -> 0.00121 | X83: =T83+U83+V83+W83 -> 0.13552
A84: RCP-Frsh-00005 | B84: Plates | C84: Frsh | D84: Pasta Creamy Potato | E84: Saturday | F84: Hot Section | G84: Garnish / Tray Line | H84: =IFERROR(VLOOKUP(I84,'Raw material list'!$A$3:$C$695,3,0),"") -> DRY1-602 | I84: Cheese Parmesan Grated | J84: Gram | K84: =IFERROR(VLOOKUP(I84,'Raw material list'!$A$3:$E$695,5,0),"") -> Gram | L84: 40 | M84: =L84/N84*100 -> 40 | N84: 100 | O84: 10 | P84: =IFERROR(L84/O84,0) -> 4 | Q84: =IFERROR(VLOOKUP(I84,'Raw material list'!$A$3:$F$695,6,0),"") -> 0.055 | R84: =IFERROR(Q84*P84,0) -> 0.22 | S84: =R84*10% -> 0.022 | T84: =R84+S84 -> 0.242 | U84: =T84*10% -> 0.0242 | V84: =T84*1% -> 0.00242 | W84: =T84*1% -> 0.00242 | X84: =T84+U84+V84+W84 -> 0.27104
A85: RCP-Frsh-00005 | B85: Plates | C85: Frsh | D85: Pasta Creamy Potato | E85: Saturday | F85: Hot Section | G85: Sauce | H85: =IFERROR(VLOOKUP(I85,'Raw material list'!$A$3:$C$695,3,0),"") -> PRD1-230 | I85: Fresh Potato | J85: Gram | K85: =IFERROR(VLOOKUP(I85,'Raw material list'!$A$3:$E$695,5,0),"") -> Gram | L85: 362.75 | M85: =L85/N85*100 -> 489.54116 | N85: 74.1 | O85: 10 | P85: =IFERROR(L85/O85,0) -> 36.275 | Q85: =IFERROR(VLOOKUP(I85,'Raw material list'!$A$3:$F$695,6,0),"") -> 0.0033738192 | R85: =IFERROR(Q85*P85,0) -> 0.12238529 | S85: =R85*10% -> 0.012238529 | T85: =R85+S85 -> 0.13462382 | U85: =T85*10% -> 0.013462382 | V85: =T85*1% -> 0.0013462382 | W85: =T85*1% -> 0.0013462382 | X85: =T85+U85+V85+W85 -> 0.15077868
A86: RCP-Frsh-00005 | B86: Plates | C86: Frsh | D86: Pasta Creamy Potato | E86: Saturday | F86: Hot Section | G86: Sauce | H86: =IFERROR(VLOOKUP(I86,'Raw material list'!$A$3:$C$695,3,0),"") -> PRD1-4265 | I86: Fresh onion Yellow(Imported) | J86: Gram | K86: =IFERROR(VLOOKUP(I86,'Raw material list'!$A$3:$E$695,5,0),"") -> Gram | L86: 30.22 | M86: =L86/N86*100 -> 35.552941 | N86: 85 | O86: 10 | P86: =IFERROR(L86/O86,0) -> 3.022 | Q86: =IFERROR(VLOOKUP(I86,'Raw material list'!$A$3:$F$695,6,0),"") -> 0.0035294118 | R86: =IFERROR(Q86*P86,0) -> 0.010665882 | S86: =R86*10% -> 0.0010665882 | T86: =R86+S86 -> 0.011732471 | U86: =T86*10% -> 0.0011732471 | V86: =T86*1% -> 0.00011732471 | W86: =T86*1% -> 0.00011732471 | X86: =T86+U86+V86+W86 -> 0.013140367
A87: RCP-Frsh-00005 | B87: Plates | C87: Frsh | D87: Pasta Creamy Potato | E87: Saturday | F87: Hot Section | G87: Sauce | H87: =IFERROR(VLOOKUP(I87,'Raw material list'!$A$3:$C$695,3,0),"") -> DRS3-1615 | I87: Olive Oil (CAN) | J87: Ml | K87: =IFERROR(VLOOKUP(I87,'Raw material list'!$A$3:$E$695,5,0),"") -> Ml | L87: 24.18 | M87: =L87/N87*100 -> 24.18 | N87: 100 | O87: 10 | P87: =IFERROR(L87/O87,0) -> 2.418 | Q87: =IFERROR(VLOOKUP(I87,'Raw material list'!$A$3:$F$695,6,0),"") -> 0.012 | R87: =IFERROR(Q87*P87,0) -> 0.029016 | S87: =R87*10% -> 0.0029016 | T87: =R87+S87 -> 0.0319176 | U87: =T87*10% -> 0.00319176 | V87: =T87*1% -> 0.000319176 | W87: =T87*1% -> 0.000319176 | X87: =T87+U87+V87+W87 -> 0.035747712
A88: RCP-Frsh-00005 | B88: Plates | C88: Frsh | D88: Pasta Creamy Potato | E88: Saturday | F88: Hot Section | G88: Sauce | H88: =IFERROR(VLOOKUP(I88,'Raw material list'!$A$3:$C$695,3,0),"") -> DRY2-1008 | I88: Butter 82% Fat(Unsalted) 25 kg | J88: Gram | K88: =IFERROR(VLOOKUP(I88,'Raw material list'!$A$3:$E$695,5,0),"") -> Gram | L88: 24.18 | M88: =L88/N88*100 -> 24.18 | N88: 100 | O88: 10 | P88: =IFERROR(L88/O88,0) -> 2.418 | Q88: =IFERROR(VLOOKUP(I88,'Raw material list'!$A$3:$F$695,6,0),"") -> 0.038 | R88: =IFERROR(Q88*P88,0) -> 0.091884 | S88: =R88*10% -> 0.0091884 | T88: =R88+S88 -> 0.1010724 | U88: =T88*10% -> 0.01010724 | V88: =T88*1% -> 0.001010724 | W88: =T88*1% -> 0.001010724 | X88: =T88+U88+V88+W88 -> 0.11320109
A89: RCP-Frsh-00005 | B89: Plates | C89: Frsh | D89: Pasta Creamy Potato | E89: Saturday | F89: Hot Section | G89: Sauce | H89: =IFERROR(VLOOKUP(I89,'Raw material list'!$A$3:$C$695,3,0),"") -> DRY2-1858 | I89: Cooking Cream 1 Ltr | J89: Ml | K89: =IFERROR(VLOOKUP(I89,'Raw material list'!$A$3:$E$695,5,0),"") -> Ml | L89: 562.75 | M89: =L89/N89*100 -> 562.75 | N89: 100 | O89: 10 | P89: =IFERROR(L89/O89,0) -> 56.275 | Q89: =IFERROR(VLOOKUP(I89,'Raw material list'!$A$3:$F$695,6,0),"") -> 0.00988 | R89: =IFERROR(Q89*P89,0) -> 0.555997 | S89: =R89*10% -> 0.0555997 | T89: =R89+S89 -> 0.6115967 | U89: =T89*10% -> 0.06115967 | V89: =T89*1% -> 0.006115967 | W89: =T89*1% -> 0.006115967 | X89: =T89+U89+V89+W89 -> 0.6849883
A90: RCP-Frsh-00005 | B90: Plates | C90: Frsh | D90: Pasta Creamy Potato | E90: Saturday | F90: Hot Section | G90: Sauce | H90: =IFERROR(VLOOKUP(I90,'Raw material list'!$A$3:$C$695,3,0),"") -> WAT-001 | I90: Tap Water-cooking | J90: Ml | K90: =IFERROR(VLOOKUP(I90,'Raw material list'!$A$3:$E$695,5,0),"") -> Ml | L90: 360.45 | M90: =L90/N90*100 -> 360.45 | N90: 100 | O90: 10 | P90: =IFERROR(L90/O90,0) -> 36.045 | Q90: =IFERROR(VLOOKUP(I90,'Raw material list'!$A$3:$F$695,6,0),"") -> 8e-05 | R90: =IFERROR(Q90*P90,0) -> 0.0028836 | S90: =R90*10% -> 0.00028836 | T90: =R90+S90 -> 0.00317196 | U90: =T90*10% -> 0.000317196 | V90: =T90*1% -> 3.17196e-05 | W90: =T90*1% -> 3.17196e-05 | X90: =T90+U90+V90+W90 -> 0.0035525952
A91: RCP-Frsh-00005 | B91: Plates | C91: Frsh | D91: Pasta Creamy Potato | E91: Saturday | F91: Hot Section | G91: Sauce | H91: =IFERROR(VLOOKUP(I91,'Raw material list'!$A$3:$C$695,3,0),"") -> DRS1-3811 | I91: Chicken Stock Powder(Packet) | J91: Gram | K91: =IFERROR(VLOOKUP(I91,'Raw material list'!$A$3:$E$695,5,0),"") -> Gram | L91: 21.76 | M91: =L91/N91*100 -> 21.76 | N91: 100 | O91: 10 | P91: =IFERROR(L91/O91,0) -> 2.176 | Q91: =IFERROR(VLOOKUP(I91,'Raw material list'!$A$3:$F$695,6,0),"") -> 0.028475 | R91: =IFERROR(Q91*P91,0) -> 0.0619616 | S91: =R91*10% -> 0.00619616 | T91: =R91+S91 -> 0.06815776 | U91: =T91*10% -> 0.006815776 | V91: =T91*1% -> 0.0006815776 | W91: =T91*1% -> 0.0006815776 | X91: =T91+U91+V91+W91 -> 0.076336691
A92: RCP-Frsh-00005 | B92: Plates | C92: Frsh | D92: Pasta Creamy Potato | E92: Saturday | F92: Hot Section | G92: Sauce | H92: =IFERROR(VLOOKUP(I92,'Raw material list'!$A$3:$C$695,3,0),"") -> DRS6-5265 | I92: Dry Parsley Flakes 453 gm | J92: Gram | K92: =IFERROR(VLOOKUP(I92,'Raw material list'!$A$3:$E$695,5,0),"") -> Gram | L92: 1.2 | M92: =L92/N92*100 -> 1.2 | N92: 100 | O92: 10 | P92: =IFERROR(L92/O92,0) -> 0.12 | Q92: =IFERROR(VLOOKUP(I92,'Raw material list'!$A$3:$F$695,6,0),"") -> 0.19315673 | R92: =IFERROR(Q92*P92,0) -> 0.023178808 | S92: =R92*10% -> 0.0023178808 | T92: =R92+S92 -> 0.025496689 | U92: =T92*10% -> 0.0025496689 | V92: =T92*1% -> 0.00025496689 | W92: =T92*1% -> 0.00025496689 | X92: =T92+U92+V92+W92 -> 0.028556291
A93: RCP-Frsh-00005 | B93: Plates | C93: Frsh | D93: Pasta Creamy Potato | E93: Saturday | F93: Hot Section | G93: Sauce | H93: =IFERROR(VLOOKUP(I93,'Raw material list'!$A$3:$C$695,3,0),"") -> DRS6-1570 | I93: Dried Oregano | J93: Gram | K93: =IFERROR(VLOOKUP(I93,'Raw material list'!$A$3:$E$695,5,0),"") -> Gram | L93: 1.2 | M93: =L93/N93*100 -> 1.2 | N93: 100 | O93: 10 | P93: =IFERROR(L93/O93,0) -> 0.12 | Q93: =IFERROR(VLOOKUP(I93,'Raw material list'!$A$3:$F$695,6,0),"") -> 0.028 | R93: =IFERROR(Q93*P93,0) -> 0.00336 | S93: =R93*10% -> 0.000336 | T93: =R93+S93 -> 0.003696 | U93: =T93*10% -> 0.0003696 | V93: =T93*1% -> 3.696e-05 | W93: =T93*1% -> 3.696e-05 | X93: =T93+U93+V93+W93 -> 0.00413952
... A96: RCP-Frsh-00005 | B96: Plates | C96: Frsh | D96: Pasta Creamy Potato | E96: Saturday | F96: Hot Section | G96: Alepo butter | H96: =IFERROR(VLOOKUP(I96,'Raw material list'!$A$3:$C$695,3,0),"") -> DRS6-1727 | I96: Spice Paprika Sweet (KG) | J96: Gram | K96: =IFERROR(VLOOKUP(I96,'Raw material list'!$A$3:$E$695,5,0),"") -> Gram | L96: 3 | M96: =L96/N96*100 -> 3 | N96: 100 | O96: 10 | P96: =IFERROR(L96/O96,0) -> 0.3 | Q96: =IFERROR(VLOOKUP(I96,'Raw material list'!$A$3:$F$695,6,0),"") -> 0.025 | R96: =IFERROR(Q96*P96,0) -> 0.0075 | S96: =R96*10% -> 0.00075 | T96: =R96+S96 -> 0.00825 | U96: =T96*10% -> 0.000825 | V96: =T96*1% -> 8.25e-05 | W96: =T96*1% -> 8.25e-05 | X96: =T96+U96+V96+W96 -> 0.00924
A97: RCP-Frsh-00006 | B97: Plates | C97: Frsh | D97: Chicken creamy lemon | E97: Saturday,Tuesday | F97: Butchery Section | G97: Marinated chicken: | H97: =IFERROR(VLOOKUP(I97,'Raw material list'!$A$3:$C$695,3,0),"") -> PLT2-3278 | I97: Frz Chicken Breast Tender (KG) | J97: Gram | K97: =IFERROR(VLOOKUP(I97,'Raw material list'!$A$3:$E$695,5,0),"") -> Gram | L97: 1200 | M97: =L97/N97*100 -> 1574.8031 | N97: 76.2 | O97: 10 | P97: =IFERROR(L97/O97,0) -> 120 | Q97: =IFERROR(VLOOKUP(I97,'Raw material list'!$A$3:$F$695,6,0),"") -> 0.030357143 | R97: =IFERROR(Q97*P97,0) -> 3.6428571 | S97: =R97*10% -> 0.36428571 | T97: =R97+S97 -> 4.0071429 | U97: =T97*10% -> 0.40071429 | V97: =T97*1% -> 0.040071429 | W97: =T97*1% -> 0.040071429 | X97: =T97+U97+V97+W97 -> 4.488 | Y97: Chicken Breast Butterfly - 140 g
A98: RCP-Frsh-00006 | B98: Plates | C98: Frsh | D98: Chicken creamy lemon | E98: Saturday,Tuesday | F98: Butchery Section | G98: Marinated chicken: | H98: =IFERROR(VLOOKUP(I98,'Raw material list'!$A$3:$C$695,3,0),"") -> DRS6-1727 | I98: Spice Paprika Sweet (KG) | J98: Gram | K98: =IFERROR(VLOOKUP(I98,'Raw material list'!$A$3:$E$695,5,0),"") -> Gram | L98: 12 | M98: =L98/N98*100 -> 12 | N98: 100 | O98: 10 | P98: =IFERROR(L98/O98,0) -> 1.2 | Q98: =IFERROR(VLOOKUP(I98,'Raw material list'!$A$3:$F$695,6,0),"") -> 0.025 | R98: =IFERROR(Q98*P98,0) -> 0.03 | S98: =R98*10% -> 0.003 | T98: =R98+S98 -> 0.033 | U98: =T98*10% -> 0.0033 | V98: =T98*1% -> 0.00033 | W98: =T98*1% -> 0.00033 | X98: =T98+U98+V98+W98 -> 0.03696
A99: RCP-Frsh-00006 | B99: Plates | C99: Frsh | D99: Chicken creamy lemon | E99: Saturday,Tuesday | F99: Butchery Section | G99: Marinated chicken: | H99: =IFERROR(VLOOKUP(I99,'Raw material list'!$A$3:$C$695,3,0),"") -> DRS6-5088 | I99: Spice Cajun (2 Kg) | J99: Gram | K99: =IFERROR(VLOOKUP(I99,'Raw material list'!$A$3:$E$695,5,0),"") -> Gram | L99: 12 | M99: =L99/N99*100 -> 12 | N99: 100 | O99: 10 | P99: =IFERROR(L99/O99,0) -> 1.2 | Q99: =IFERROR(VLOOKUP(I99,'Raw material list'!$A$3:$F$695,6,0),"") -> 0.08 | R99: =IFERROR(Q99*P99,0) -> 0.096 | S99: =R99*10% -> 0.0096 | T99: =R99+S99 -> 0.1056 | U99: =T99*10% -> 0.01056 | V99: =T99*1% -> 0.001056 | W99: =T99*1% -> 0.001056 | X99: =T99+U99+V99+W99 -> 0.118272
A100: RCP-Frsh-00006 | B100: Plates | C100: Frsh | D100: Chicken creamy lemon | E100: Saturday,Tuesday | F100: Butchery Section | G100: Marinated chicken: | H100: =IFERROR(VLOOKUP(I100,'Raw material list'!$A$3:$C$695,3,0),"") -> DRS6-5376 | I100: Dry Thyme 500gm | J100: Gram | K100: =IFERROR(VLOOKUP(I100,'Raw material list'!$A$3:$E$695,5,0),"") -> Gram | L100: 3 | M100: =L100/N100*100 -> 3 | N100: 100 | O100: 10 | P100: =IFERROR(L100/O100,0) -> 0.3 | Q100: =IFERROR(VLOOKUP(I100,'Raw material list'!$A$3:$F$695,6,0),"") -> 0.028 | R100: =IFERROR(Q100*P100,0) -> 0.0084 | S100: =R100*10% -> 0.00084 | T100: =R100+S100 -> 0.00924 | U100: =T100*10% -> 0.000924 | V100: =T100*1% -> 9.24e-05 | W100: =T100*1% -> 9.24e-05 | X100: =T100+U100+V100+W100 -> 0.0103488
A101: RCP-Frsh-00006 | B101: Plates | C101: Frsh | D101: Chicken creamy lemon | E101: Saturday,Tuesday | F101: Butchery Section | G101: Marinated chicken: | H101: =IFERROR(VLOOKUP(I101,'Raw material list'!$A$3:$C$695,3,0),"") -> WAT-001 | I101: Tap Water-cooking | J101: Ml | K101: =IFERROR(VLOOKUP(I101,'Raw material list'!$A$3:$E$695,5,0),"") -> Ml | L101: 120 | M101: =L101/N101*100 -> 120 | N101: 100 | O101: 10 | P101: =IFERROR(L101/O101,0) -> 12 | Q101: =IFERROR(VLOOKUP(I101,'Raw material list'!$A$3:$F$695,6,0),"") -> 8e-05 | R101: =IFERROR(Q101*P101,0) -> 0.00096 | S101: =R101*10% -> 9.6e-05 | T101: =R101+S101 -> 0.001056 | U101: =T101*10% -> 0.0001056 | V101: =T101*1% -> 1.056e-05 | W101: =T101*1% -> 1.056e-05 | X101: =T101+U101+V101+W101 -> 0.00118272
A102: RCP-Frsh-00006 | B102: Plates | C102: Frsh | D102: Chicken creamy lemon | E102: Saturday,Tuesday | F102: Hot Section | G102: Garnish / Trya line | H102: =IFERROR(VLOOKUP(I102,'Raw material list'!$A$3:$C$695,3,0),"") -> PRD1-209 | I102: Fresh Lemon | J102: Gram | K102: =IFERROR(VLOOKUP(I102,'Raw material list'!$A$3:$E$695,5,0),"") -> Gram | L102: 10 | M102: =L102/N102*100 -> 26.315789 | N102: 38 | O102: 10 | P102: =IFERROR(L102/O102,0) -> 1 | Q102: =IFERROR(VLOOKUP(I102,'Raw material list'!$A$3:$F$695,6,0),"") -> 0.010088272 | R102: =IFERROR(Q102*P102,0) -> 0.010088272 | S102: =R102*10% -> 0.0010088272 | T102: =R102+S102 -> 0.0110971 | U102: =T102*10% -> 0.00110971 | V102: =T102*1% -> 0.000110971 | W102: =T102*1% -> 0.000110971 | X102: =T102+U102+V102+W102 -> 0.012428752
A103: RCP-Frsh-00006 | B103: Plates | C103: Frsh | D103: Chicken creamy lemon | E103: Saturday,Tuesday | F103: Hot Section | G103: Garnish / Trya line | H103: =IFERROR(VLOOKUP(I103,'Raw material list'!$A$3:$C$695,3,0),"") -> PRD1-194 | I103: Fresh Chives (Ciboulettes) | J103: Gram | K103: =IFERROR(VLOOKUP(I103,'Raw material list'!$A$3:$E$695,5,0),"") -> Gram | L103: 10 | M103: =L103/N103*100 -> 10.869565 | N103: 92 | O103: 10 | P103: =IFERROR(L103/O103,0) -> 1 | Q103: =IFERROR(VLOOKUP(I103,'Raw material list'!$A$3:$F$695,6,0),"") -> 0.11 | R103: =IFERROR(Q103*P103,0) -> 0.11 | S103: =R103*10% -> 0.011 | T103: =R103+S103 -> 0.121 | U103: =T103*10% -> 0.0121 | V103: =T103*1% -> 0.00121 | W103: =T103*1% -> 0.00121 | X103: =T103+U103+V103+W103 -> 0.13552
A104: RCP-Frsh-00006 | B104: Plates | C104: Frsh | D104: Chicken creamy lemon | E104: Saturday,Tuesday | F104: Hot Section | G104: Sauce | H104: =IFERROR(VLOOKUP(I104,'Raw material list'!$A$3:$C$695,3,0),"") -> DRY2-1008 | I104: Butter 82% Fat(Unsalted) 25 kg | J104: Gram | K104: =IFERROR(VLOOKUP(I104,'Raw material list'!$A$3:$E$695,5,0),"") -> Gram | L104: 57.47 | M104: =L104/N104*100 -> 57.47 | N104: 100 | O104: 10 | P104: =IFERROR(L104/O104,0) -> 5.747 | Q104: =IFERROR(VLOOKUP(I104,'Raw material list'!$A$3:$F$695,6,0),"") -> 0.038 | R104: =IFERROR(Q104*P104,0) -> 0.218386 | S104: =R104*10% -> 0.0218386 | T104: =R104+S104 -> 0.2402246 | U104: =T104*10% -> 0.02402246 | V104: =T104*1% -> 0.002402246 | W104: =T104*1% -> 0.002402246 | X104: =T104+U104+V104+W104 -> 0.26905155
A105: RCP-Frsh-00006 | B105: Plates | C105: Frsh | D105: Chicken creamy lemon | E105: Saturday,Tuesday | F105: Hot Section | G105: Sauce | H105: =IFERROR(VLOOKUP(I105,'Raw material list'!$A$3:$C$695,3,0),"") -> PRD1-4327 | I105: Fresh Garlic Peeled | J105: Gram | K105: =IFERROR(VLOOKUP(I105,'Raw material list'!$A$3:$E$695,5,0),"") -> Gram | L105: 10 | M105: =L105/N105*100 -> 12.5 | N105: 80 | O105: 10 | P105: =IFERROR(L105/O105,0) -> 1 | Q105: =IFERROR(VLOOKUP(I105,'Raw material list'!$A$3:$F$695,6,0),"") -> 0.013 | R105: =IFERROR(Q105*P105,0) -> 0.013 | S105: =R105*10% -> 0.0013 | T105: =R105+S105 -> 0.0143 | U105: =T105*10% -> 0.00143 | V105: =T105*1% -> 0.000143 | W105: =T105*1% -> 0.000143 | X105: =T105+U105+V105+W105 -> 0.016016
A106: RCP-Frsh-00006 | B106: Plates | C106: Frsh | D106: Chicken creamy lemon | E106: Saturday,Tuesday | F106: Hot Section | G106: Sauce | H106: =IFERROR(VLOOKUP(I106,'Raw material list'!$A$3:$C$695,3,0),"") -> PRD1-4265 | I106: Fresh onion Yellow(Imported) | J106: Gram | K106: =IFERROR(VLOOKUP(I106,'Raw material list'!$A$3:$E$695,5,0),"") -> Gram | L106: 116.95 | M106: =L106/N106*100 -> 137.58824 | N106: 85 | O106: 10 | P106: =IFERROR(L106/O106,0) -> 11.695 | Q106: =IFERROR(VLOOKUP(I106,'Raw material list'!$A$3:$F$695,6,0),"") -> 0.0035294118 | R106: =IFERROR(Q106*P106,0) -> 0.041276471 | S106: =R106*10% -> 0.0041276471 | T106: =R106+S106 -> 0.045404118 | U106: =T106*10% -> 0.0045404118 | V106: =T106*1% -> 0.00045404118 | W106: =T106*1% -> 0.00045404118 | X106: =T106+U106+V106+W106 -> 0.050852612
A107: RCP-Frsh-00006 | B107: Plates | C107: Frsh | D107: Chicken creamy lemon | E107: Saturday,Tuesday | F107: Hot Section | G107: Sauce | H107: =IFERROR(VLOOKUP(I107,'Raw material list'!$A$3:$C$695,3,0),"") -> DRS6-261 | I107: Cinnamon Stick | J107: Gram | K107: =IFERROR(VLOOKUP(I107,'Raw material list'!$A$3:$E$695,5,0),"") -> Gram | L107: 14.61 | M107: =L107/N107*100 -> 14.61 | N107: 100 | O107: 10 | P107: =IFERROR(L107/O107,0) -> 1.461 | Q107: =IFERROR(VLOOKUP(I107,'Raw material list'!$A$3:$F$695,6,0),"") -> 0.014 | R107: =IFERROR(Q107*P107,0) -> 0.020454 | S107: =R107*10% -> 0.0020454 | T107: =R107+S107 -> 0.0224994 | U107: =T107*10% -> 0.00224994 | V107: =T107*1% -> 0.000224994 | W107: =T107*1% -> 0.000224994 | X107: =T107+U107+V107+W107 -> 0.025199328
A108: RCP-Frsh-00006 | B108: Plates | C108: Frsh | D108: Chicken creamy lemon | E108: Saturday,Tuesday | F108: Hot Section | G108: Sauce | H108: =IFERROR(VLOOKUP(I108,'Raw material list'!$A$3:$C$695,3,0),"") -> DRS5-980 | I108: Flour Cake Special (all purpose) | J108: Gram | K108: =IFERROR(VLOOKUP(I108,'Raw material list'!$A$3:$E$695,5,0),"") -> Gram | L108: 23.39 | M108: =L108/N108*100 -> 23.39 | N108: 100 | O108: 10 | P108: =IFERROR(L108/O108,0) -> 2.339 | Q108: =IFERROR(VLOOKUP(I108,'Raw material list'!$A$3:$F$695,6,0),"") -> 0.001 | R108: =IFERROR(Q108*P108,0) -> 0.002339 | S108: =R108*10% -> 0.0002339 | T108: =R108+S108 -> 0.0025729 | U108: =T108*10% -> 0.00025729 | V108: =T108*1% -> 2.5729e-05 | W108: =T108*1% -> 2.5729e-05 | X108: =T108+U108+V108+W108 -> 0.002881648
A109: RCP-Frsh-00006 | B109: Plates | C109: Frsh | D109: Chicken creamy lemon | E109: Saturday,Tuesday | F109: Hot Section | G109: Sauce | H109: =IFERROR(VLOOKUP(I109,'Raw material list'!$A$3:$C$695,3,0),"") -> WAT-001 | I109: Tap Water-cooking | J109: Ml | K109: =IFERROR(VLOOKUP(I109,'Raw material list'!$A$3:$E$695,5,0),"") -> Ml | L109: 292.39 | M109: =L109/N109*100 -> 292.39 | N109: 100 | O109: 10 | P109: =IFERROR(L109/O109,0) -> 29.239 | Q109: =IFERROR(VLOOKUP(I109,'Raw material list'!$A$3:$F$695,6,0),"") -> 8e-05 | R109: =IFERROR(Q109*P109,0) -> 0.00233912 | S109: =R109*10% -> 0.000233912 | T109: =R109+S109 -> 0.002573032 | U109: =T109*10% -> 0.0002573032 | V109: =T109*1% -> 2.573032e-05 | W109: =T109*1% -> 2.573032e-05 | X109: =T109+U109+V109+W109 -> 0.0028817958
... A125: RCP-Frsh-00006 | B125: Plates | C125: Frsh | D125: Chicken creamy lemon | E125: Saturday,Tuesday | F125: Hot Section | G125: White Rice | H125: =IFERROR(VLOOKUP(I125,'Raw material list'!$A$3:$C$695,3,0),"") -> DRS6-261 | I125: Cinnamon Stick | J125: Gram | K125: =IFERROR(VLOOKUP(I125,'Raw material list'!$A$3:$E$695,5,0),"") -> Gram | L125: 0.3 | M125: =L125/N125*100 -> 0.3 | N125: 100 | O125: 10 | P125: =IFERROR(L125/O125,0) -> 0.03 | Q125: =IFERROR(VLOOKUP(I125,'Raw material list'!$A$3:$F$695,6,0),"") -> 0.014 | R125: =IFERROR(Q125*P125,0) -> 0.00042 | S125: =R125*10% -> 4.2e-05 | T125: =R125+S125 -> 0.000462 | U125: =T125*10% -> 4.62e-05 | V125: =T125*1% -> 4.62e-06 | W125: =T125*1% -> 4.62e-06 | X125: =T125+U125+V125+W125 -> 0.00051744
A126: RCP-Frsh-00007 | B126: Plates | C126: Frsh | D126: Curry nomi Pasta | E126: Sunday | F126: Butchery Section | G126: Marinated chicken: | H126: =IFERROR(VLOOKUP(I126,'Raw material list'!$A$3:$C$695,3,0),"") -> PLT2-3278 | I126: Frz Chicken Breast Tender (KG) | J126: Gram | K126: =IFERROR(VLOOKUP(I126,'Raw material list'!$A$3:$E$695,5,0),"") -> Gram | L126: 1200 | M126: =L126/N126*100 -> 1574.8031 | N126: 76.2 | O126: 10 | P126: =IFERROR(L126/O126,0) -> 120 | Q126: =IFERROR(VLOOKUP(I126,'Raw material list'!$A$3:$F$695,6,0),"") -> 0.030357143 | R126: =IFERROR(Q126*P126,0) -> 3.6428571 | S126: =R126*10% -> 0.36428571 | T126: =R126+S126 -> 4.0071429 | U126: =T126*10% -> 0.40071429 | V126: =T126*1% -> 0.040071429 | W126: =T126*1% -> 0.040071429 | X126: =T126+U126+V126+W126 -> 4.488 | Y126: Chicken Breast Butterfly - 140 g
A127: RCP-Frsh-00007 | B127: Plates | C127: Frsh | D127: Curry nomi Pasta | E127: Sunday | F127: Butchery Section | G127: Marinated chicken: | H127: =IFERROR(VLOOKUP(I127,'Raw material list'!$A$3:$C$695,3,0),"") -> DRS6-1727 | I127: Spice Paprika Sweet (KG) | J127: Gram | K127: =IFERROR(VLOOKUP(I127,'Raw material list'!$A$3:$E$695,5,0),"") -> Gram | L127: 12 | M127: =L127/N127*100 -> 12 | N127: 100 | O127: 10 | P127: =IFERROR(L127/O127,0) -> 1.2 | Q127: =IFERROR(VLOOKUP(I127,'Raw material list'!$A$3:$F$695,6,0),"") -> 0.025 | R127: =IFERROR(Q127*P127,0) -> 0.03 | S127: =R127*10% -> 0.003 | T127: =R127+S127 -> 0.033 | U127: =T127*10% -> 0.0033 | V127: =T127*1% -> 0.00033 | W127: =T127*1% -> 0.00033 | X127: =T127+U127+V127+W127 -> 0.03696
A128: RCP-Frsh-00007 | B128: Plates | C128: Frsh | D128: Curry nomi Pasta | E128: Sunday | F128: Butchery Section | G128: Marinated chicken: | H128: =IFERROR(VLOOKUP(I128,'Raw material list'!$A$3:$C$695,3,0),"") -> DRS6-5088 | I128: Spice Cajun (2 Kg) | J128: Gram | K128: =IFERROR(VLOOKUP(I128,'Raw material list'!$A$3:$E$695,5,0),"") -> Gram | L128: 12 | M128: =L128/N128*100 -> 12 | N128: 100 | O128: 10 | P128: =IFERROR(L128/O128,0) -> 1.2 | Q128: =IFERROR(VLOOKUP(I128,'Raw material list'!$A$3:$F$695,6,0),"") -> 0.08 | R128: =IFERROR(Q128*P128,0) -> 0.096 | S128: =R128*10% -> 0.0096 | T128: =R128+S128 -> 0.1056 | U128: =T128*10% -> 0.01056 | V128: =T128*1% -> 0.001056 | W128: =T128*1% -> 0.001056 | X128: =T128+U128+V128+W128 -> 0.118272
A129: RCP-Frsh-00007 | B129: Plates | C129: Frsh | D129: Curry nomi Pasta | E129: Sunday | F129: Butchery Section | G129: Marinated chicken: | H129: =IFERROR(VLOOKUP(I129,'Raw material list'!$A$3:$C$695,3,0),"") -> DRS6-5376 | I129: Dry Thyme 500gm | J129: Gram | K129: =IFERROR(VLOOKUP(I129,'Raw material list'!$A$3:$E$695,5,0),"") -> Gram | L129: 3 | M129: =L129/N129*100 -> 3 | N129: 100 | O129: 10 | P129: =IFERROR(L129/O129,0) -> 0.3 | Q129: =IFERROR(VLOOKUP(I129,'Raw material list'!$A$3:$F$695,6,0),"") -> 0.028 | R129: =IFERROR(Q129*P129,0) -> 0.0084 | S129: =R129*10% -> 0.00084 | T129: =R129+S129 -> 0.00924 | U129: =T129*10% -> 0.000924 | V129: =T129*1% -> 9.24e-05 | W129: =T129*1% -> 9.24e-05 | X129: =T129+U129+V129+W129 -> 0.0103488
A130: RCP-Frsh-00007 | B130: Plates | C130: Frsh | D130: Curry nomi Pasta | E130: Sunday | F130: Butchery Section | G130: Marinated chicken: | H130: =IFERROR(VLOOKUP(I130,'Raw material list'!$A$3:$C$695,3,0),"") -> WAT-001 | I130: Tap Water-cooking | J130: Ml | K130: =IFERROR(VLOOKUP(I130,'Raw material list'!$A$3:$E$695,5,0),"") -> Ml | L130: 120 | M130: =L130/N130*100 -> 120 | N130: 100 | O130: 10 | P130: =IFERROR(L130/O130,0) -> 12 | Q130: =IFERROR(VLOOKUP(I130,'Raw material list'!$A$3:$F$695,6,0),"") -> 8e-05 | R130: =IFERROR(Q130*P130,0) -> 0.00096 | S130: =R130*10% -> 9.6e-05 | T130: =R130+S130 -> 0.001056 | U130: =T130*10% -> 0.0001056 | V130: =T130*1% -> 1.056e-05 | W130: =T130*1% -> 1.056e-05 | X130: =T130+U130+V130+W130 -> 0.00118272
A131: RCP-Frsh-00007 | B131: Plates | C131: Frsh | D131: Curry nomi Pasta | E131: Sunday | F131: Hot Section | H131: =IFERROR(VLOOKUP(I131,'Raw material list'!$A$3:$C$695,3,0),"") -> DRS2-4321 | I131: Pasta Penne Rigate (1 Kg) | J131: Gram | K131: =IFERROR(VLOOKUP(I131,'Raw material list'!$A$3:$E$695,5,0),"") -> Gram | L131: 700 | M131: =L131/N131*100 -> 700 | N131: 100 | O131: 10 | P131: =IFERROR(L131/O131,0) -> 70 | Q131: =IFERROR(VLOOKUP(I131,'Raw material list'!$A$3:$F$695,6,0),"") -> 0.00803 | R131: =IFERROR(Q131*P131,0) -> 0.5621 | S131: =R131*10% -> 0.05621 | T131: =R131+S131 -> 0.61831 | U131: =T131*10% -> 0.061831 | V131: =T131*1% -> 0.0061831 | W131: =T131*1% -> 0.0061831 | X131: =T131+U131+V131+W131 -> 0.6925072
A132: RCP-Frsh-00007 | B132: Plates | C132: Frsh | D132: Curry nomi Pasta | E132: Sunday | F132: Hot Section | G132: Garnish / Tray line | H132: =IFERROR(VLOOKUP(I132,'Raw material list'!$A$3:$C$695,3,0),"") -> DRY2-1008 | I132: Butter 82% Fat(Unsalted) 25 kg | J132: Gram | K132: =IFERROR(VLOOKUP(I132,'Raw material list'!$A$3:$E$695,5,0),"") -> Gram | L132: 30 | M132: =L132/N132*100 -> 30 | N132: 100 | O132: 10 | P132: =IFERROR(L132/O132,0) -> 3 | Q132: =IFERROR(VLOOKUP(I132,'Raw material list'!$A$3:$F$695,6,0),"") -> 0.038 | R132: =IFERROR(Q132*P132,0) -> 0.114 | S132: =R132*10% -> 0.0114 | T132: =R132+S132 -> 0.1254 | U132: =T132*10% -> 0.01254 | V132: =T132*1% -> 0.001254 | W132: =T132*1% -> 0.001254 | X132: =T132+U132+V132+W132 -> 0.140448
...

Sheet Raw material list
C1: Master Raw Material
A2: Items Description | C2: Code | D2: NameEN | E2: Unit | F2: Price | G2: Main category | H2: Sub category
A3: Bran Bread Brown (Diet) | C3: BKR1-1917 | D3: Bran Bread Brown (Diet) | E3: Each | F3: 0.95 | G3: Fresh | H3: Bakery
A4: Bread Arabic Brown (6 each) 400211 | C4: BKR1-3695 | D4: Bread Arabic Brown (6 each) 400211 | E4: Each | F4: 0.16666667 | G4: Fresh | H4: Bakery
A5: Bread Arabic White(7 Each) 400210 | C5: BKR1-3694 | D5: Bread Arabic White(7 Each) 400210 | E5: Each | F5: 0.14285714 | G5: Fresh | H5: Bakery
A6: Bread Burger Bun Brown(Each) | C6: BKR1-3791 | D6: Bread Burger Bun Brown(Each) | E6: Each | F6: 1 | G6: Fresh | H6: Bakery
A7: Bread Crumb IMP(Packet) | C7: BKR1-4011 | D7: Bread Crumb IMP(Packet) | E7: Gram | F7: 0.022 | G7: Fresh | H7: Bakery
A8: Bread Jumbo Sandwich White 400007 | C8: BKR1-1328 | D8: Bread Jumbo Sandwich White 400007 | E8: Each | F8: 1 | G8: Fresh | H8: Bakery
A9: Bread Potato Burger Plain | C9: BKR1-4332 | D9: Bread Potato Burger Plain | E9: Each | F9: 0.55833333 | G9: Fresh | H9: Bakery
A10: Spices Bay Leaves | C10: DRS6-3593 | D10: Bay Leaf | E10: Gram | F10: 0.0105 | G10: Dry
A11: Bread Shawarma | C11: BKR1-1575 | D11: Bread Shawarma | E11: Each | F11: 0.12 | G11: Fresh | H11: Bakery
A12: Bread Sliced Brown Med-400001 | C12: BKR1-1327 | D12: Bread Sliced Brown Med-400001 | E12: Slice | F12: 0.22222222 | G12: Fresh | H12: Bakery
A13: Bread Sliced White Med-400000 | C13: BKR1-1326 | D13: Bread Sliced White Med-400000 | E13: Slice | F13: 0.16666667 | G13: Fresh | H13: Bakery
A14: Fresh Bread Baguette Long Brown | C14: BKR1-3428 | D14: Fresh Bread Baguette Long Brown | E14: Each | F14: 4.78 | G14: Fresh | H14: Bakery
A15: Sriracha hot sauce | C15: DRS1-4954 | D15: Sriracha hot sauce | E15: ML | F15: 0.029
A16: Frz Kunafa Dough | C16: BKR1-1910 | D16: Frz Kunafa Dough | E16: Gram | F16: 0.01366 | G16: Frozen | H16: Bakery
A17: Milk Bread Mini 9Pcs | C17: BKR1-2125 | D17: Milk Bread Mini 9Pcs | E17: Each | F17: 0.44444444 | G17: Fresh | H17: Bakery
A18: Tang mango | C18: DRS1-4905 | D18: Tang mango | E18: Gram | F18: 0.0208
A19: Tang orange | C19: DRS1-4902 | D19: Tang orange | E19: Gram | F19: 0.0208
A20: Qursan | C20: BKR1-4717 | D20: Qursan | E20: Gram | F20: 0.013 | G20: Fresh | H20: Bakery
A21: Tart Shell Round Mini 3.7 Cm,Sweet | C21: BKR1-4132 | D21: Tart Shell Round Mini 3.7 Cm,Sweet | E21: Each | F21: 0.84126984 | G21: Fresh | H21: Bakery
A22: Bread Tortilla White,20cm(Fonte) | C22: BKR2-4274 | D22: Bread Tortilla White,20cm(Fonte) | E22: Each | F22: 0.625 | G22: Frozen | H22: Bakery
A23: Bread Tortilla White,30cm(Fonte) | C23: BKR2-4275 | D23: Bread Tortilla White,30cm(Fonte) | E23: Each | F23: 0.83333333 | G23: Frozen | H23: Bakery
A24: Frz Bread Baguette French (40080009) | C24: BKR2-2058 | D24: Frz Bread Baguette French (40080009) | E24: Gram | F24: 0.0066666667 | G24: Frozen | H24: Bakery
A25: Frz Bread Baguette Multicereal (40080109) | C25: BKR2-2059 | D25: Frz Bread Baguette Multicereal (40080109) | E25: Gram | F25: 0.01 | G25: Frozen | H25: Bakery
A26: Frz Bread Jumbo Sandwich 400017 | C26: BKR2-5081 | D26: Frz Bread Jumbo Sandwich 400017 | E26: Each | F26: 0.96666667 | G26: Frozen | H26: Bakery
A27: Frz Bread Panini (90 Gram) | C27: BKR2-4596 | D27: Frz Bread Panini (90 Gram) | E27: Each | F27: 0.96 | G27: Frozen | H27: Bakery
A28: Frz Bread Tortilla,Keto,8 Inch | C28: BKR2-4961 | D28: Frz Bread Tortilla,Keto,8 Inch | E28: Each | F28: 3 | G28: Frozen | H28: Bakery
A29: Frz Sambusak Leaves (1 kg) | C29: BKR2-5137 | D29: Frz Sambusak Leaves (1 kg) | E29: Gram | F29: 0.01413 | G29: Frozen | H29: Bakery
A30: Frz Spring Roll Dough(160 Gram) | C30: BKR2-1104 | D30: Frz Spring Roll Dough(160 Gram) | E30: Gram | F30: 0.0255 | G30: Frozen | H30: Bakery
A31: Frz.Puff Pastry Sheets(400Gram) | C31: BKR2-3658 | D31: Frz.Puff Pastry Sheets(400Gram) | E31: Gram | F31: 0.019175 | G31: Frozen | H31: Bakery
A32: Jam Apricot Portion(100 Each) | C32: DRS1-5003 | D32: Jam Apricot Portion(100 Each) | E32: Each | F32: 0.38 | G32: Dry | H32: Canned Item
A33: Italian seasoning | C33: DRS6-5020 | D33: Italian seasoning | E33: Gram | F33: 0.15
A34: Cinnamon Stick | C34: DRS6-261 | D34: Cinnamon Stick | E34: Gram | F34: 0.014 | G34: Dry | H34: Spices
A35: Light Mayonnaise | C35: DRS1-1652 | D35: Light Mayonnaise | E35: Gram | F35: 0.0128
A36: Ajinomoto (MSG) 454 gm | C36: DRS1-5155 | D36: Ajinomoto (MSG) 454 gm | E36: Gram | F36: 0.019823789 | G36: Dry | H36: Canned Item
A37: Apple Vinegar | C37: DRS1-4227 | D37: Apple Vinegar | E37: Ml | F37: 0.0058139535 | G37: Dry | H37: Canned Item
A38: Beef Stock Powder(Packet) | C38: DRS1-3813 | D38: Beef Stock Powder(Packet) | E38: Gram | F38: 0.044441667 | G38: Dry | H38: Canned Item
A39: Biscuit Digestive (150 Gram) | C39: DRS1-3696 | D39: Biscuit Digestive (150 Gram) | E39: Gram | F39: 0.0094666667 | G39: Dry | H39: Canned Item
A40: Butter Peanuts(794 Gram) | C40: DRS1-4103 | D40: Butter Peanuts(794 Gram) | E40: Gram | F40: 0.026763224 | G40: Dry | H40: Canned Item
A41: Can Apple Pie Filling | C41: DRS1-3948 | D41: Can Apple Pie Filling | E41: Gram | F41: 0.024038462 | G41: Dry | H41: Canned Item
A42: Can Artichoke Bottoms | C42: DRS1-4234 | D42: Can Artichoke Bottoms | E42: Gram | F42: 0.0456 | G42: Dry | H42: Canned Item
A43: Can Baked Beans(420 Gram) | C43: DRS1-4772 | D43: Can Baked Beans(420 Gram) | E43: Gram | F43: 0.0064 | G43: Dry | H43: Canned Item
A44: Can Beans Red Kidney (425 Gram) | C44: DRS1-1359 | D44: Can Beans Red Kidney (425 Gram) | E44: Gram | F44: 0.0139 | G44: Dry | H44: Canned Item
A45: Can Beetroot Sliced | C45: DRS1-3595 | D45: Can Beetroot Sliced | E45: Gram | F45: 0.0086 | G45: Dry | H45: Canned Item
A46: Can Chopped Tomato | C46: DRS1-4840 | D46: Can Chopped Tomato | E46: Gram | F46: 0.006 | G46: Dry | H46: Canned Item
A47: Can Condensed Milk | C47: DRS1-3865 | D47: Can Condensed Milk | E47: Gram | F47: 0.020629723 | G47: Dry | H47: Canned Item
... A61: Can Tomato Paste (4500 Gram) | C61: DRS1-1747 | D61: Can Tomato Paste (4500 Gram) | E61: Gram | F61: 0.0051851852 | G61: Dry | H61: Canned Item
A62: Fresh Mango | C62: PRV1-393 | D62: Fresh Mango | E62: Each | F62: 0.01 | G62: Fresh
A63: Dates Paste | C63: DRS1-3480 | D63: Dates Paste | E63: Gram | F63: 0.0043 | G63: Dry | H63: Canned Item
A64: Corn flakes | C64: DRS1-1545 | D64: Corn Flaks | E64: Gram | F64: 0.015
A65: Can Tomato Peeled | C65: DRS1-607 | D65: Can Tomato Peeled | E65: Gram | F65: 0.0058823529 | G65: Dry | H65: Canned Item
A66: Can White Kidney Beans(400 gram) | C66: DRS1-3886 | D66: Can White Kidney Beans(400 gram) | E66: Gram | F66: 0.0068 | G66: Dry | H66: Canned Item
A67: Can Young Baby Corn | C67: DRS1-2121 | D67: Can Young Baby Corn | E67: Gram | F67: 0.0204 | G67: Dry | H67: Canned Item
A68: Chicken Stock Powder(Packet) | C68: DRS1-3811 | D68: Chicken Stock Powder(Packet) | E68: Gram | F68: 0.028475 | G68: Dry | H68: Canned Item
A69: Cucumber Pickles (3.2 Kg) | C69: DRS1-167 | D69: Cucumber Pickles (3.2 Kg) | E69: Gram | F69: 0.0129 | G69: Dry | H69: Canned Item
A70: Date Portion (Ramadan) | C70: DRS1-4979 | D70: Date Portion (Ramadan) | E70: Each | F70: 0.35 | G70: Dry | H70: Canned Item
A71: Flower Water(Blossom) | C71: DRS1-41 | D71: Flower Water(Blossom) | E71: Ml | F71: 0.019709091 | G71: Dry | H71: Canned Item
A72: Food Color Yellow(Saffron) | C72: DRS1-304 | D72: Food Color Yellow(Saffron) | E72: Gram | F72: 0.0208 | G72: Dry | H72: Canned Item
A73: Ghee Vegetable(15 KG) | C73: DRS1-1599 | D73: Ghee Vegetable(15 KG) | E73: Gram | F73: 0.012666667 | G73: Dry | H73: Canned Item
A74: Ginger Pickles(Bottle) | C74: DRS1-4213 | D74: Ginger Pickles(Bottle) | E74: Gram | F74: 0.042 | G74: Dry | H74: Canned Item
A75: Grape Leaves / Vine Leaves | C75: DRS1-96 | D75: Grape Leaves / Vine Leaves | E75: Gram | F75: 0.0377 | G75: Dry | H75: Canned Item
A76: Grape Leaves,Stuffed(1950 Gram) | C76: DRS1-3911 | D76: Grape Leaves,Stuffed(1950 Gram) | E76: Gram | F76: 0.0239 | G76: Dry | H76: Canned Item
... A118: Cheese Mozzarella Mini | C118: DRY1-1701 | D118: Cheese Mozzarella Mini | E118: Gram | F118: 0.065 | G118: Fresh | H118: Cheese
A119: Halloumi | C119: DRY1-353 | D119: Halloumi | E119: Gram | F119: 0.0245
A120: Cheese Parmesan Grated | C120: DRY1-602 | D120: Cheese Parmesan Grated | E120: Gram | F120: 0.055 | G120: Fresh | H120: Cheese
A121: Feta Cheese | C121: DRY1-1846 | D121: Feta Cheese | E121: Gram | F121: 0.00862 | G121: Fresh | H121: Cheese
A122: Cheese Parmesan Padano1 KG (permegano) | C122: DRY1-342 | D122: Cheese Parmesan Padano1 KG (permegano) | E122: Gram | F122: 0.053 | G122: Fresh | H122: Cheese
A123: Cheese Triangles,Al Marai,360 Gm | C123: DRY1-5114 | D123: Cheese Triangles,Al Marai,360 Gm | E123: Each | F123: 0.43343 | G123: Fresh | H123: Cheese
A124: Frz Paneer (Cottage Cheese) 500 gm | C124: DRY1-5345 | D124: Frz Paneer (Cottage Cheese) 500 gm | E124: Gram | F124: 0.039 | G124: Fresh | H124: Cheese
A125: Goat Cheese (KG) | C125: DRY1-1794 | D125: Goat Cheese (KG) | E125: Gram | F125: 0.07162 | G125: Fresh | H125: Cheese
A126: Breakfast Cream Firm,Ashta,5Kg | C126: DRY2-1907 | D126: Breakfast Cream Firm,Ashta,5Kg | E126: Gram | F126: 0.0136 | G126: Fresh | H126: Cheese
A127: Coffee Mate Creamer,Single Serve | C127: DRS1-3155 | D127: Coffee Mate Creamer,Single Serve | E127: Each | F127: 0.21425 | G127: Dry | H127: Coffe & Tea
A128: Coffee Powder Regular ,Mastercafe | C128: DRS1-5431 | D128: Coffee Powder Regular ,Mastercafe | E128: Gram | F128: 0.0771 | G128: Dry | H128: Coffe & Tea
A129: Delicate Pouch Alegria Nestle | C129: DRS1-5126 | D129: Delicate Pouch Alegria Nestle | E129: Gram | F129: 0.35048 | G129: Dry | H129: Coffe & Tea
A130: Karak Tea,Cardamom Premix Nestle | C130: DRS1-4831 | D130: Karak Tea,Cardamom Premix Nestle | E130: Gram | F130: 0.08745 | G130: Dry | H130: Coffe & Tea
A131: Nescafe Classic (3 in 1) | C131: DRS1-3713 | D131: Nescafe Classic (3 in 1) | E131: Each | F131: 1.132 | G131: Dry | H131: Coffe & Tea
... A259: Syrup Chocolate (Hershey's) 680 Gram | C259: DRS1-616 | D259: Syrup Chocolate (Hershey's) 680 Gram | E259: Gram | F259: 0.024264706 | G259: Dry | H259: Pastry & Bakery
A260: Tea Biscuits(160 Gram) | C260: DRS1-3600 | D260: Tea Biscuits(160 Gram) | E260: Gram | G260: Dry | H260: Pastry & Bakery
A261: Toffee Caramel,Gold(5 Kg) | C261: DRS1-3634 | D261: Toffee Caramel,Gold(5 Kg) | E261: Gram | F261: 0.0186 | G261: Dry | H261: Pastry & Bakery
A262: Vanilla Essence (Concentrated) | C262: DRS1-1823 | D262: Vanilla Essence (Concentrated) | E262: Gram | F262: 0.049 | G262: Dry | H262: Pastry & Bakery
A263: White Chocolate Coins 29% (Icam) | C263: DRS1-4358 | D263: White Chocolate Coins 29% (Icam) | E263: Gram | F263: 0.042 | G263: Dry | H263: Pastry & Bakery
A264: Xanthan Gum | C264: DRS1-5140 | D264: Xanthan Gum | E264: Gram | F264: 0.3 | G264: Dry | H264: Pastry & Bakery
A265: Bread Improver K2 | C265: DRS5-1325 | D265: Bread Improver K2 | E265: Gram | F265: 0.0117 | G265: Dry | H265: Pastry & Bakery
A266: Brownies Mix Powder(10 kg) | C266: DRS5-5001 | D266: Brownies Mix Powder(10 kg) | E266: Gram | F266: 0.0119 | G266: Dry | H266: Pastry & Bakery
A267: Cake Mix Powder,Red Velvet (10 kg) | C267: DRS5-5476 | D267: Cake Mix Powder,Red Velvet (10 kg) | E267: Gram | F267: 0.0085 | G267: Dry | H267: Pastry & Bakery
A268: Cocoa Powder (25 KG) | C268: DRS5-1736 | D268: Cocoa Powder (25 KG) | E268: Gram | F268: 0.038 | G268: Dry | H268: Pastry & Bakery
A269: Cream Caramel Mix Powder 5 kg | C269: DRS5-5427 | D269: Cream Caramel Mix Powder 5 kg | E269: Gram | F269: 0.019 | G269: Dry | H269: Pastry & Bakery
A270: Cream patissiere Custard Powder | C270: DRS5-4244 | D270: Cream patissiere Custard Powder | E270: Gram | F270: 0.023 | G270: Dry | H270: Pastry & Bakery
A271: Custard powder(450 Gram) | C271: DRS5-618 | D271: Custard powder(450 Gram) | E271: Gram | F271: 0.015288889 | G271: Dry | H271: Pastry & Bakery
A272: Easy Muffin Mix Chocolate (10 KG) | C272: DRS5-1624 | D272: Easy Muffin Mix Chocolate (10 KG) | E272: Gram | F272: 0.01 | G272: Dry | H272: Pastry & Bakery
... A348: Sugar Sachet,Low Calorie(Tropicana Slim) | C348: DRS1-686 | D348: Sugar Sachet,Low Calorie(Tropicana Slim) | E348: Each | F348: 0.2042 | G348: Dry | H348: Sugar
A349: Ice Cubes | C349: WAT-002 | D349: Ice Cubes | E349: Gram | F349: 0.00016
A350: Sugar Sweetener Powder(Steviana) | C350: DRS1-4257 | D350: Sugar Sweetener Powder(Steviana) | E350: Gram | F350: 0.07085 | G350: Dry | H350: Sugar
A351: Dressing,1000 Island | C351: DRS1-4469 | D351: Dressing,1000 Island | E351: Gram | F351: 0.0091931217 | G351: Dry | H351: Vinegar & Sauces
A352: Ketchup Gallon (5 Kg) | C352: DRS1-1039 | D352: Ketchup Gallon (5 Kg) | E352: Gram | F352: 0.0035 | G352: Dry | H352: Vinegar & Sauces
A353: ketchup Sachet | C353: DRS1-685 | D353: ketchup Sachet | E353: Each | F353: 0.048 | G353: Dry | H353: Vinegar & Sauces
A354: Mayonnaise Regular | C354: DRS1-58 | D354: Mayonnaise Regular | E354: Gram | F354: 0.0064814815 | G354: Dry | H354: Vinegar & Sauces
A355: Rice Vinegar 500 ml Mizkan | C355: DRS1-5258 | D355: Rice Vinegar 500 ml Mizkan | E355: Ml | F355: 0.02866 | G355: Dry | H355: Vinegar & Sauces
A356: Rose Water | C356: DRS1-115 | D356: Rose Water | E356: Ml | F356: 0.019709091 | G356: Dry | H356: Vinegar & Sauces
...
